{
	"circuit": {
		"circuitRef": "monaco",
		"country": "Monaco",
		"location": "Monte-Carlo",
		"name": "Circuit de Monaco"
	},
	"date": "1984-06-03",
	"driversData": [
		{
			"constructorRef": "mclaren",
			"driverRef": "prost",
			"grid": 1,
			"lapPositions": [],
			"pitStops": [],
			"points": 4.5,
			"position": 1,
			"positionOrder": 1,
			"positionText": "1",
			"qualifying": { "q1": null, "q2": null, "q3": null }
		},
		{
			"constructorRef": "toleman",
			"driverRef": "senna",
			"grid": 13,
			"lapPositions": [],
			"pitStops": [],
			"points": 3,
			"position": 2,
			"positionOrder": 2,
			"positionText": "2",
			"qualifying": { "q1": null, "q2": null, "q3": null }
		},
		{
			"constructorRef": "ferrari",
			"driverRef": "arnoux",
			"grid": 3,
			"lapPositions": [],
			"pitStops": [],
			"points": 2,
			"position": 3,
			"positionOrder": 3,
			"positionText": "3",
			"qualifying": { "q1": null, "q2": null, "q3": null }
		},
		{
			"constructorRef": "williams",
			"driverRef": "keke_rosberg",
			"grid": 10,
			"lapPositions": [],
			"pitStops": [],
			"points": 1.5,
			"position": 4,
			"positionOrder": 4,
			"positionText": "4",
			"qualifying": { "q1": null, "q2": null, "q3": null }
		},
		{
			"constructorRef": "team_lotus",
			"driverRef": "angelis",
			"grid": 11,
			"lapPositions": [],
			"pitStops": [],
			"points": 1,
			"position": 5,
			"positionOrder": 5,
			"positionText": "5",
			"qualifying": { "q1": null, "q2": null, "q3": null }
		},
		{
			"constructorRef": "ferrari",
			"driverRef": "alboreto",
			"grid": 4,
			"lapPositions": [],
			"pitStops": [],
			"points": 0.5,
			"position": 6,
			"positionOrder": 6,
			"positionText": "6",
			"qualifying": { "q1": null, "q2": null, "q3": null }
		},
		{
			"constructorRef": "osella",
			"driverRef": "ghinzani",
			"grid": 19,
			"lapPositions": [],
			"pitStops": [],
			"points": 0,
			"position": 7,
			"positionOrder": 7,
			"positionText": "7",
			"qualifying": { "q1": null, "q2": null, "q3": null }
		},
		{
			"constructorRef": "williams",
			"driverRef": "laffite",
			"grid": 16,
			"lapPositions": [],
			"pitStops": [],
			"points": 0,
			"position": 8,
			"positionOrder": 8,
			"positionText": "8",
			"qualifying": { "q1": null, "q2": null, "q3": null }
		},
		{
			"constructorRef": "tyrrell",
			"driverRef": "bellof",
			"grid": 20,
			"lapPositions": [],
			"pitStops": [],
			"points": 0,
			"position": null,
			"positionOrder": 9,
			"positionText": "D",
			"qualifying": { "q1": null, "q2": null, "q3": null }
		},
		{
			"constructorRef": "alfa",
			"driverRef": "patrese",
			"grid": 14,
			"lapPositions": [],
			"pitStops": [],
			"points": 0,
			"position": null,
			"positionOrder": 10,
			"positionText": "R",
			"qualifying": { "q1": null, "q2": null, "q3": null }
		},
		{
			"constructorRef": "mclaren",
			"driverRef": "lauda",
			"grid": 8,
			"lapPositions": [],
			"pitStops": [],
			"points": 0,
			"position": null,
			"positionOrder": 11,
			"positionText": "R",
			"qualifying": { "q1": null, "q2": null, "q3": null }
		},
		{
			"constructorRef": "ats",
			"driverRef": "manfred_winkelhock",
			"grid": 12,
			"lapPositions": [],
			"pitStops": [],
			"points": 0,
			"position": null,
			"positionOrder": 12,
			"positionText": "R",
			"qualifying": { "q1": null, "q2": null, "q3": null }
		},
		{
			"constructorRef": "team_lotus",
			"driverRef": "mansell",
			"grid": 2,
			"lapPositions": [],
			"pitStops": [],
			"points": 0,
			"position": null,
			"positionOrder": 13,
			"positionText": "R",
			"qualifying": { "q1": null, "q2": null, "q3": null }
		},
		{
			"constructorRef": "brabham",
			"driverRef": "piquet",
			"grid": 9,
			"lapPositions": [],
			"pitStops": [],
			"points": 0,
			"position": null,
			"positionOrder": 14,
			"positionText": "R",
			"qualifying": { "q1": null, "q2": null, "q3": null }
		},
		{
			"constructorRef": "ligier",
			"driverRef": "hesnault",
			"grid": 17,
			"lapPositions": [],
			"pitStops": [],
			"points": 0,
			"position": null,
			"positionOrder": 15,
			"positionText": "R",
			"qualifying": { "q1": null, "q2": null, "q3": null }
		},
		{
			"constructorRef": "brabham",
			"driverRef": "corrado_fabi",
			"grid": 15,
			"lapPositions": [],
			"pitStops": [],
			"points": 0,
			"position": null,
			"positionOrder": 16,
			"positionText": "R",
			"qualifying": { "q1": null, "q2": null, "q3": null }
		},
		{
			"constructorRef": "toleman",
			"driverRef": "cecotto",
			"grid": 18,
			"lapPositions": [],
			"pitStops": [],
			"points": 0,
			"position": null,
			"positionOrder": 17,
			"positionText": "R",
			"qualifying": { "q1": null, "q2": null, "q3": null }
		},
		{
			"constructorRef": "renault",
			"driverRef": "warwick",
			"grid": 5,
			"lapPositions": [],
			"pitStops": [],
			"points": 0,
			"position": null,
			"positionOrder": 18,
			"positionText": "R",
			"qualifying": { "q1": null, "q2": null, "q3": null }
		},
		{
			"constructorRef": "renault",
			"driverRef": "tambay",
			"grid": 6,
			"lapPositions": [],
			"pitStops": [],
			"points": 0,
			"position": null,
			"positionOrder": 19,
			"positionText": "R",
			"qualifying": { "q1": null, "q2": null, "q3": null }
		},
		{
			"constructorRef": "ligier",
			"driverRef": "cesaris",
			"grid": 7,
			"lapPositions": [],
			"pitStops": [],
			"points": 0,
			"position": null,
			"positionOrder": 20,
			"positionText": "R",
			"qualifying": { "q1": null, "q2": null, "q3": null }
		},
		{
			"constructorRef": "arrows",
			"driverRef": "surer",
			"grid": 0,
			"lapPositions": [],
			"pitStops": [],
			"points": 0,
			"position": null,
			"positionOrder": 21,
			"positionText": "F",
			"qualifying": { "q1": null, "q2": null, "q3": null }
		},
		{
			"constructorRef": "tyrrell",
			"driverRef": "brundle",
			"grid": 0,
			"lapPositions": [],
			"pitStops": [],
			"points": 0,
			"position": null,
			"positionOrder": 22,
			"positionText": "F",
			"qualifying": { "q1": null, "q2": null, "q3": null }
		},
		{
			"constructorRef": "alfa",
			"driverRef": "cheever",
			"grid": 0,
			"lapPositions": [],
			"pitStops": [],
			"points": 0,
			"position": null,
			"positionOrder": 23,
			"positionText": "F",
			"qualifying": { "q1": null, "q2": null, "q3": null }
		},
		{
			"constructorRef": "arrows",
			"driverRef": "boutsen",
			"grid": 0,
			"lapPositions": [],
			"pitStops": [],
			"points": 0,
			"position": null,
			"positionOrder": 24,
			"positionText": "F",
			"qualifying": { "q1": null, "q2": null, "q3": null }
		},
		{
			"constructorRef": "ram",
			"driverRef": "palmer",
			"grid": 0,
			"lapPositions": [],
			"pitStops": [],
			"points": 0,
			"position": null,
			"positionOrder": 25,
			"positionText": "F",
			"qualifying": { "q1": null, "q2": null, "q3": null }
		},
		{
			"constructorRef": "spirit",
			"driverRef": "baldi",
			"grid": 0,
			"lapPositions": [],
			"pitStops": [],
			"points": 0,
			"position": null,
			"positionOrder": 26,
			"positionText": "F",
			"qualifying": { "q1": null, "q2": null, "q3": null }
		},
		{
			"constructorRef": "ram",
			"driverRef": "alliot",
			"grid": 0,
			"lapPositions": [],
			"pitStops": [],
			"points": 0,
			"position": null,
			"positionOrder": 27,
			"positionText": "F",
			"qualifying": { "q1": null, "q2": null, "q3": null }
		}
	],
	"name": "Monaco Grand Prix",
	"raceId": 441,
	"round": 6,
	"slug": "monaco-grand-prix",
	"year": 1984
}
