{
	"rounds": [
		{
			"circuit": {
				"country": "South Africa",
				"location": "Midrand",
				"name": "Kyalami"
			},
			"constructorStandings": [
				{ "constructorRef": "renault", "points": 13, "position": 1, "wins": 1 },
				{ "constructorRef": "williams", "points": 8, "position": 2, "wins": 0 },
				{ "constructorRef": "mclaren", "points": 4, "position": 3, "wins": 0 },
				{ "constructorRef": "tyrrell", "points": 0, "position": 4, "wins": 0 },
				{
					"constructorRef": "team_lotus",
					"points": 0,
					"position": 5,
					"wins": 0
				},
				{ "constructorRef": "ats", "points": 0, "position": 6, "wins": 0 },
				{ "constructorRef": "alfa", "points": 0, "position": 7, "wins": 0 },
				{ "constructorRef": "march", "points": 0, "position": 8, "wins": 0 },
				{ "constructorRef": "theodore", "points": 0, "position": 9, "wins": 0 },
				{
					"constructorRef": "fittipaldi",
					"points": 0,
					"position": 10,
					"wins": 0
				},
				{ "constructorRef": "ferrari", "points": 0, "position": 11, "wins": 0 },
				{ "constructorRef": "ligier", "points": 0, "position": 12, "wins": 0 },
				{ "constructorRef": "toleman", "points": 0, "position": 13, "wins": 0 },
				{ "constructorRef": "brabham", "points": 0, "position": 14, "wins": 0 },
				{ "constructorRef": "osella", "points": 0, "position": 15, "wins": 0 },
				{ "constructorRef": "arrows", "points": 0, "position": 16, "wins": 0 },
				{ "constructorRef": "ensign", "points": 0, "position": 17, "wins": 0 }
			],
			"date": "23rd Jan 1982",
			"driverStandings": [
				{ "driverRef": "prost", "points": 9, "position": 1, "wins": 1 },
				{ "driverRef": "reutemann", "points": 6, "position": 2, "wins": 0 },
				{ "driverRef": "arnoux", "points": 4, "position": 3, "wins": 0 },
				{ "driverRef": "lauda", "points": 3, "position": 4, "wins": 0 },
				{ "driverRef": "keke_rosberg", "points": 2, "position": 5, "wins": 0 },
				{ "driverRef": "watson", "points": 1, "position": 6, "wins": 0 },
				{ "driverRef": "alboreto", "points": 0, "position": 7, "wins": 0 },
				{ "driverRef": "angelis", "points": 0, "position": 8, "wins": 0 },
				{ "driverRef": "salazar", "points": 0, "position": 9, "wins": 0 },
				{
					"driverRef": "manfred_winkelhock",
					"points": 0,
					"position": 10,
					"wins": 0
				},
				{ "driverRef": "giacomelli", "points": 0, "position": 11, "wins": 0 },
				{ "driverRef": "mass", "points": 0, "position": 12, "wins": 0 },
				{ "driverRef": "cesaris", "points": 0, "position": 13, "wins": 0 },
				{ "driverRef": "daly", "points": 0, "position": 14, "wins": 0 },
				{ "driverRef": "boesel", "points": 0, "position": 15, "wins": 0 },
				{ "driverRef": "borgudd", "points": 0, "position": 16, "wins": 0 },
				{ "driverRef": "serra", "points": 0, "position": 17, "wins": 0 },
				{ "driverRef": "pironi", "points": 0, "position": 18, "wins": 0 },
				{ "driverRef": "laffite", "points": 0, "position": 19, "wins": 0 },
				{ "driverRef": "warwick", "points": 0, "position": 20, "wins": 0 },
				{ "driverRef": "patrese", "points": 0, "position": 21, "wins": 0 },
				{ "driverRef": "cheever", "points": 0, "position": 22, "wins": 0 },
				{
					"driverRef": "gilles_villeneuve",
					"points": 0,
					"position": 23,
					"wins": 0
				},
				{ "driverRef": "piquet", "points": 0, "position": 24, "wins": 0 },
				{ "driverRef": "mansell", "points": 0, "position": 25, "wins": 0 },
				{ "driverRef": "jarier", "points": 0, "position": 26, "wins": 0 },
				{ "driverRef": "baldi", "points": 0, "position": 27, "wins": 0 },
				{ "driverRef": "paletti", "points": 0, "position": 28, "wins": 0 },
				{ "driverRef": "henton", "points": 0, "position": 29, "wins": 0 },
				{ "driverRef": "guerrero", "points": 0, "position": 30, "wins": 0 },
				{ "driverRef": "fabi", "points": 0, "position": 31, "wins": 0 }
			],
			"name": "South African Grand Prix",
			"podium": [
				{ "constructorRef": "renault", "driverRef": "prost", "position": 1 },
				{
					"constructorRef": "williams",
					"driverRef": "reutemann",
					"position": 2
				},
				{ "constructorRef": "renault", "driverRef": "arnoux", "position": 3 }
			],
			"round": 1,
			"slug": "south-african-grand-prix"
		},
		{
			"circuit": {
				"country": "Brazil",
				"location": "Rio de Janeiro",
				"name": "Autódromo Internacional Nelson Piquet"
			},
			"constructorStandings": [
				{ "constructorRef": "renault", "points": 22, "position": 1, "wins": 2 },
				{ "constructorRef": "mclaren", "points": 10, "position": 2, "wins": 0 },
				{ "constructorRef": "williams", "points": 8, "position": 3, "wins": 0 },
				{
					"constructorRef": "team_lotus",
					"points": 4,
					"position": 4,
					"wins": 0
				},
				{ "constructorRef": "tyrrell", "points": 3, "position": 5, "wins": 0 },
				{ "constructorRef": "ats", "points": 2, "position": 6, "wins": 0 },
				{ "constructorRef": "ferrari", "points": 1, "position": 7, "wins": 0 },
				{ "constructorRef": "march", "points": 0, "position": 8, "wins": 0 },
				{ "constructorRef": "osella", "points": 0, "position": 9, "wins": 0 },
				{ "constructorRef": "arrows", "points": 0, "position": 10, "wins": 0 },
				{ "constructorRef": "alfa", "points": 0, "position": 11, "wins": 0 },
				{
					"constructorRef": "theodore",
					"points": 0,
					"position": 12,
					"wins": 0
				},
				{
					"constructorRef": "fittipaldi",
					"points": 0,
					"position": 13,
					"wins": 0
				},
				{ "constructorRef": "brabham", "points": 0, "position": 14, "wins": 0 },
				{ "constructorRef": "ligier", "points": 0, "position": 15, "wins": 0 },
				{ "constructorRef": "toleman", "points": 0, "position": 16, "wins": 0 },
				{ "constructorRef": "ensign", "points": 0, "position": 17, "wins": 0 }
			],
			"date": "21st Mar 1982",
			"driverStandings": [
				{ "driverRef": "prost", "points": 18, "position": 1, "wins": 2 },
				{ "driverRef": "watson", "points": 7, "position": 2, "wins": 0 },
				{ "driverRef": "reutemann", "points": 6, "position": 3, "wins": 0 },
				{ "driverRef": "arnoux", "points": 4, "position": 4, "wins": 0 },
				{ "driverRef": "mansell", "points": 4, "position": 5, "wins": 0 },
				{ "driverRef": "alboreto", "points": 3, "position": 6, "wins": 0 },
				{ "driverRef": "lauda", "points": 3, "position": 7, "wins": 0 },
				{
					"driverRef": "manfred_winkelhock",
					"points": 2,
					"position": 8,
					"wins": 0
				},
				{ "driverRef": "keke_rosberg", "points": 2, "position": 9, "wins": 0 },
				{ "driverRef": "pironi", "points": 1, "position": 10, "wins": 0 },
				{ "driverRef": "borgudd", "points": 0, "position": 11, "wins": 0 },
				{ "driverRef": "mass", "points": 0, "position": 12, "wins": 0 },
				{ "driverRef": "angelis", "points": 0, "position": 13, "wins": 0 },
				{ "driverRef": "salazar", "points": 0, "position": 14, "wins": 0 },
				{ "driverRef": "jarier", "points": 0, "position": 15, "wins": 0 },
				{ "driverRef": "baldi", "points": 0, "position": 16, "wins": 0 },
				{ "driverRef": "giacomelli", "points": 0, "position": 17, "wins": 0 },
				{ "driverRef": "cesaris", "points": 0, "position": 18, "wins": 0 },
				{ "driverRef": "daly", "points": 0, "position": 19, "wins": 0 },
				{ "driverRef": "boesel", "points": 0, "position": 20, "wins": 0 },
				{ "driverRef": "serra", "points": 0, "position": 21, "wins": 0 },
				{ "driverRef": "patrese", "points": 0, "position": 22, "wins": 0 },
				{
					"driverRef": "gilles_villeneuve",
					"points": 0,
					"position": 23,
					"wins": 0
				},
				{ "driverRef": "laffite", "points": 0, "position": 24, "wins": 0 },
				{ "driverRef": "warwick", "points": 0, "position": 25, "wins": 0 },
				{ "driverRef": "cheever", "points": 0, "position": 26, "wins": 0 },
				{ "driverRef": "piquet", "points": 0, "position": 27, "wins": 0 },
				{ "driverRef": "fabi", "points": 0, "position": 28, "wins": 0 },
				{ "driverRef": "henton", "points": 0, "position": 29, "wins": 0 },
				{ "driverRef": "paletti", "points": 0, "position": 30, "wins": 0 },
				{ "driverRef": "guerrero", "points": 0, "position": 31, "wins": 0 }
			],
			"name": "Brazilian Grand Prix",
			"podium": [
				{ "constructorRef": "renault", "driverRef": "prost", "position": 1 },
				{ "constructorRef": "mclaren", "driverRef": "watson", "position": 2 },
				{
					"constructorRef": "team_lotus",
					"driverRef": "mansell",
					"position": 3
				}
			],
			"round": 2,
			"slug": "brazilian-grand-prix"
		},
		{
			"circuit": {
				"country": "USA",
				"location": "California",
				"name": "Long Beach"
			},
			"constructorStandings": [
				{ "constructorRef": "renault", "points": 22, "position": 1, "wins": 2 },
				{ "constructorRef": "mclaren", "points": 20, "position": 2, "wins": 1 },
				{
					"constructorRef": "williams",
					"points": 14,
					"position": 3,
					"wins": 0
				},
				{
					"constructorRef": "team_lotus",
					"points": 6,
					"position": 4,
					"wins": 0
				},
				{ "constructorRef": "tyrrell", "points": 6, "position": 5, "wins": 0 },
				{ "constructorRef": "brabham", "points": 4, "position": 6, "wins": 0 },
				{ "constructorRef": "ats", "points": 2, "position": 7, "wins": 0 },
				{ "constructorRef": "ferrari", "points": 1, "position": 8, "wins": 0 },
				{ "constructorRef": "march", "points": 0, "position": 9, "wins": 0 },
				{ "constructorRef": "osella", "points": 0, "position": 10, "wins": 0 },
				{ "constructorRef": "arrows", "points": 0, "position": 11, "wins": 0 },
				{ "constructorRef": "alfa", "points": 0, "position": 12, "wins": 0 },
				{
					"constructorRef": "theodore",
					"points": 0,
					"position": 13,
					"wins": 0
				},
				{
					"constructorRef": "fittipaldi",
					"points": 0,
					"position": 14,
					"wins": 0
				},
				{ "constructorRef": "ligier", "points": 0, "position": 15, "wins": 0 },
				{ "constructorRef": "ensign", "points": 0, "position": 16, "wins": 0 },
				{ "constructorRef": "toleman", "points": 0, "position": 17, "wins": 0 }
			],
			"date": "4th Apr 1982",
			"driverStandings": [
				{ "driverRef": "prost", "points": 18, "position": 1, "wins": 2 },
				{ "driverRef": "lauda", "points": 12, "position": 2, "wins": 1 },
				{ "driverRef": "keke_rosberg", "points": 8, "position": 3, "wins": 0 },
				{ "driverRef": "watson", "points": 8, "position": 4, "wins": 0 },
				{ "driverRef": "reutemann", "points": 6, "position": 5, "wins": 0 },
				{ "driverRef": "alboreto", "points": 6, "position": 6, "wins": 0 },
				{ "driverRef": "mansell", "points": 4, "position": 7, "wins": 0 },
				{ "driverRef": "patrese", "points": 4, "position": 8, "wins": 0 },
				{ "driverRef": "arnoux", "points": 4, "position": 9, "wins": 0 },
				{ "driverRef": "angelis", "points": 2, "position": 10, "wins": 0 },
				{
					"driverRef": "manfred_winkelhock",
					"points": 2,
					"position": 11,
					"wins": 0
				},
				{ "driverRef": "pironi", "points": 1, "position": 12, "wins": 0 },
				{ "driverRef": "borgudd", "points": 0, "position": 13, "wins": 0 },
				{ "driverRef": "mass", "points": 0, "position": 14, "wins": 0 },
				{ "driverRef": "boesel", "points": 0, "position": 15, "wins": 0 },
				{ "driverRef": "salazar", "points": 0, "position": 16, "wins": 0 },
				{ "driverRef": "jarier", "points": 0, "position": 17, "wins": 0 },
				{ "driverRef": "baldi", "points": 0, "position": 18, "wins": 0 },
				{ "driverRef": "giacomelli", "points": 0, "position": 19, "wins": 0 },
				{ "driverRef": "cesaris", "points": 0, "position": 20, "wins": 0 },
				{ "driverRef": "daly", "points": 0, "position": 21, "wins": 0 },
				{ "driverRef": "serra", "points": 0, "position": 22, "wins": 0 },
				{ "driverRef": "cheever", "points": 0, "position": 23, "wins": 0 },
				{ "driverRef": "henton", "points": 0, "position": 24, "wins": 0 },
				{ "driverRef": "guerrero", "points": 0, "position": 25, "wins": 0 },
				{ "driverRef": "laffite", "points": 0, "position": 26, "wins": 0 },
				{
					"driverRef": "gilles_villeneuve",
					"points": 0,
					"position": 27,
					"wins": 0
				},
				{ "driverRef": "piquet", "points": 0, "position": 28, "wins": 0 },
				{ "driverRef": "warwick", "points": 0, "position": 29, "wins": 0 },
				{
					"driverRef": "mario_andretti",
					"points": 0,
					"position": 30,
					"wins": 0
				},
				{ "driverRef": "fabi", "points": 0, "position": 31, "wins": 0 },
				{ "driverRef": "paletti", "points": 0, "position": 32, "wins": 0 }
			],
			"name": "United States Grand Prix West",
			"podium": [
				{ "constructorRef": "mclaren", "driverRef": "lauda", "position": 1 },
				{
					"constructorRef": "williams",
					"driverRef": "keke_rosberg",
					"position": 2
				},
				{ "constructorRef": "brabham", "driverRef": "patrese", "position": 3 }
			],
			"round": 3,
			"slug": "united-states-grand-prix-west"
		},
		{
			"circuit": {
				"country": "Italy",
				"location": "Imola",
				"name": "Autodromo Enzo e Dino Ferrari"
			},
			"constructorStandings": [
				{ "constructorRef": "renault", "points": 22, "position": 1, "wins": 2 },
				{ "constructorRef": "mclaren", "points": 20, "position": 2, "wins": 1 },
				{ "constructorRef": "ferrari", "points": 16, "position": 3, "wins": 1 },
				{
					"constructorRef": "williams",
					"points": 14,
					"position": 4,
					"wins": 0
				},
				{ "constructorRef": "tyrrell", "points": 10, "position": 5, "wins": 0 },
				{
					"constructorRef": "team_lotus",
					"points": 6,
					"position": 6,
					"wins": 0
				},
				{ "constructorRef": "brabham", "points": 4, "position": 7, "wins": 0 },
				{ "constructorRef": "ats", "points": 4, "position": 8, "wins": 0 },
				{ "constructorRef": "osella", "points": 3, "position": 9, "wins": 0 },
				{ "constructorRef": "march", "points": 0, "position": 10, "wins": 0 },
				{ "constructorRef": "arrows", "points": 0, "position": 11, "wins": 0 },
				{ "constructorRef": "alfa", "points": 0, "position": 12, "wins": 0 },
				{
					"constructorRef": "theodore",
					"points": 0,
					"position": 13,
					"wins": 0
				},
				{
					"constructorRef": "fittipaldi",
					"points": 0,
					"position": 14,
					"wins": 0
				},
				{ "constructorRef": "toleman", "points": 0, "position": 15, "wins": 0 },
				{ "constructorRef": "ligier", "points": 0, "position": 16, "wins": 0 },
				{ "constructorRef": "ensign", "points": 0, "position": 17, "wins": 0 }
			],
			"date": "25th Apr 1982",
			"driverStandings": [
				{ "driverRef": "prost", "points": 18, "position": 1, "wins": 2 },
				{ "driverRef": "lauda", "points": 12, "position": 2, "wins": 1 },
				{ "driverRef": "pironi", "points": 10, "position": 3, "wins": 1 },
				{ "driverRef": "alboreto", "points": 10, "position": 4, "wins": 0 },
				{ "driverRef": "keke_rosberg", "points": 8, "position": 5, "wins": 0 },
				{ "driverRef": "watson", "points": 8, "position": 6, "wins": 0 },
				{
					"driverRef": "gilles_villeneuve",
					"points": 6,
					"position": 7,
					"wins": 0
				},
				{ "driverRef": "reutemann", "points": 6, "position": 8, "wins": 0 },
				{ "driverRef": "mansell", "points": 4, "position": 9, "wins": 0 },
				{ "driverRef": "arnoux", "points": 4, "position": 10, "wins": 0 },
				{ "driverRef": "patrese", "points": 4, "position": 11, "wins": 0 },
				{ "driverRef": "jarier", "points": 3, "position": 12, "wins": 0 },
				{ "driverRef": "angelis", "points": 2, "position": 13, "wins": 0 },
				{ "driverRef": "salazar", "points": 2, "position": 14, "wins": 0 },
				{
					"driverRef": "manfred_winkelhock",
					"points": 2,
					"position": 15,
					"wins": 0
				},
				{ "driverRef": "borgudd", "points": 0, "position": 16, "wins": 0 },
				{ "driverRef": "mass", "points": 0, "position": 17, "wins": 0 },
				{ "driverRef": "boesel", "points": 0, "position": 18, "wins": 0 },
				{ "driverRef": "baldi", "points": 0, "position": 19, "wins": 0 },
				{ "driverRef": "giacomelli", "points": 0, "position": 20, "wins": 0 },
				{ "driverRef": "cesaris", "points": 0, "position": 21, "wins": 0 },
				{ "driverRef": "daly", "points": 0, "position": 22, "wins": 0 },
				{ "driverRef": "serra", "points": 0, "position": 23, "wins": 0 },
				{ "driverRef": "fabi", "points": 0, "position": 24, "wins": 0 },
				{ "driverRef": "paletti", "points": 0, "position": 25, "wins": 0 },
				{ "driverRef": "cheever", "points": 0, "position": 26, "wins": 0 },
				{ "driverRef": "henton", "points": 0, "position": 27, "wins": 0 },
				{ "driverRef": "warwick", "points": 0, "position": 28, "wins": 0 },
				{ "driverRef": "guerrero", "points": 0, "position": 29, "wins": 0 },
				{ "driverRef": "laffite", "points": 0, "position": 30, "wins": 0 },
				{ "driverRef": "piquet", "points": 0, "position": 31, "wins": 0 },
				{
					"driverRef": "mario_andretti",
					"points": 0,
					"position": 32,
					"wins": 0
				}
			],
			"name": "San Marino Grand Prix",
			"podium": [
				{ "constructorRef": "ferrari", "driverRef": "pironi", "position": 1 },
				{
					"constructorRef": "ferrari",
					"driverRef": "gilles_villeneuve",
					"position": 2
				},
				{ "constructorRef": "tyrrell", "driverRef": "alboreto", "position": 3 }
			],
			"round": 4,
			"slug": "san-marino-grand-prix"
		},
		{
			"circuit": {
				"country": "Belgium",
				"location": "Heusden-Zolder",
				"name": "Zolder"
			},
			"constructorStandings": [
				{ "constructorRef": "mclaren", "points": 29, "position": 1, "wins": 2 },
				{ "constructorRef": "renault", "points": 22, "position": 2, "wins": 2 },
				{
					"constructorRef": "williams",
					"points": 20,
					"position": 3,
					"wins": 0
				},
				{ "constructorRef": "ferrari", "points": 16, "position": 4, "wins": 1 },
				{ "constructorRef": "tyrrell", "points": 10, "position": 5, "wins": 0 },
				{
					"constructorRef": "team_lotus",
					"points": 9,
					"position": 6,
					"wins": 0
				},
				{ "constructorRef": "brabham", "points": 6, "position": 7, "wins": 0 },
				{ "constructorRef": "ligier", "points": 4, "position": 8, "wins": 0 },
				{ "constructorRef": "ats", "points": 4, "position": 9, "wins": 0 },
				{ "constructorRef": "osella", "points": 3, "position": 10, "wins": 0 },
				{
					"constructorRef": "fittipaldi",
					"points": 1,
					"position": 11,
					"wins": 0
				},
				{ "constructorRef": "arrows", "points": 0, "position": 12, "wins": 0 },
				{ "constructorRef": "march", "points": 0, "position": 13, "wins": 0 },
				{ "constructorRef": "alfa", "points": 0, "position": 14, "wins": 0 },
				{
					"constructorRef": "theodore",
					"points": 0,
					"position": 15,
					"wins": 0
				},
				{ "constructorRef": "toleman", "points": 0, "position": 16, "wins": 0 },
				{ "constructorRef": "ensign", "points": 0, "position": 17, "wins": 0 }
			],
			"date": "9th May 1982",
			"driverStandings": [
				{ "driverRef": "prost", "points": 18, "position": 1, "wins": 2 },
				{ "driverRef": "watson", "points": 17, "position": 2, "wins": 1 },
				{ "driverRef": "keke_rosberg", "points": 14, "position": 3, "wins": 0 },
				{ "driverRef": "lauda", "points": 12, "position": 4, "wins": 1 },
				{ "driverRef": "pironi", "points": 10, "position": 5, "wins": 1 },
				{ "driverRef": "alboreto", "points": 10, "position": 6, "wins": 0 },
				{
					"driverRef": "gilles_villeneuve",
					"points": 6,
					"position": 7,
					"wins": 0
				},
				{ "driverRef": "reutemann", "points": 6, "position": 8, "wins": 0 },
				{ "driverRef": "angelis", "points": 5, "position": 9, "wins": 0 },
				{ "driverRef": "mansell", "points": 4, "position": 10, "wins": 0 },
				{ "driverRef": "arnoux", "points": 4, "position": 11, "wins": 0 },
				{ "driverRef": "cheever", "points": 4, "position": 12, "wins": 0 },
				{ "driverRef": "patrese", "points": 4, "position": 13, "wins": 0 },
				{ "driverRef": "jarier", "points": 3, "position": 14, "wins": 0 },
				{ "driverRef": "salazar", "points": 2, "position": 15, "wins": 0 },
				{
					"driverRef": "manfred_winkelhock",
					"points": 2,
					"position": 16,
					"wins": 0
				},
				{ "driverRef": "piquet", "points": 2, "position": 17, "wins": 0 },
				{ "driverRef": "serra", "points": 1, "position": 18, "wins": 0 },
				{ "driverRef": "borgudd", "points": 0, "position": 19, "wins": 0 },
				{ "driverRef": "surer", "points": 0, "position": 20, "wins": 0 },
				{ "driverRef": "mass", "points": 0, "position": 21, "wins": 0 },
				{ "driverRef": "boesel", "points": 0, "position": 22, "wins": 0 },
				{ "driverRef": "laffite", "points": 0, "position": 23, "wins": 0 },
				{ "driverRef": "baldi", "points": 0, "position": 24, "wins": 0 },
				{ "driverRef": "giacomelli", "points": 0, "position": 25, "wins": 0 },
				{ "driverRef": "cesaris", "points": 0, "position": 26, "wins": 0 },
				{ "driverRef": "daly", "points": 0, "position": 27, "wins": 0 },
				{ "driverRef": "fabi", "points": 0, "position": 28, "wins": 0 },
				{ "driverRef": "paletti", "points": 0, "position": 29, "wins": 0 },
				{ "driverRef": "henton", "points": 0, "position": 30, "wins": 0 },
				{ "driverRef": "warwick", "points": 0, "position": 31, "wins": 0 },
				{ "driverRef": "guerrero", "points": 0, "position": 32, "wins": 0 },
				{
					"driverRef": "mario_andretti",
					"points": 0,
					"position": 33,
					"wins": 0
				},
				{ "driverRef": "lammers", "points": 0, "position": 34, "wins": 0 },
				{ "driverRef": "villota", "points": 0, "position": 35, "wins": 0 }
			],
			"name": "Belgian Grand Prix",
			"podium": [
				{ "constructorRef": "mclaren", "driverRef": "watson", "position": 1 },
				{
					"constructorRef": "williams",
					"driverRef": "keke_rosberg",
					"position": 2
				},
				{ "constructorRef": "ligier", "driverRef": "cheever", "position": 3 }
			],
			"round": 5,
			"slug": "belgian-grand-prix"
		},
		{
			"circuit": {
				"country": "Monaco",
				"location": "Monte-Carlo",
				"name": "Circuit de Monaco"
			},
			"constructorStandings": [
				{ "constructorRef": "mclaren", "points": 29, "position": 1, "wins": 2 },
				{ "constructorRef": "renault", "points": 22, "position": 2, "wins": 2 },
				{ "constructorRef": "ferrari", "points": 22, "position": 3, "wins": 1 },
				{
					"constructorRef": "williams",
					"points": 21,
					"position": 4,
					"wins": 0
				},
				{ "constructorRef": "brabham", "points": 15, "position": 5, "wins": 1 },
				{
					"constructorRef": "team_lotus",
					"points": 14,
					"position": 6,
					"wins": 0
				},
				{ "constructorRef": "tyrrell", "points": 10, "position": 7, "wins": 0 },
				{ "constructorRef": "ligier", "points": 4, "position": 8, "wins": 0 },
				{ "constructorRef": "alfa", "points": 4, "position": 9, "wins": 0 },
				{ "constructorRef": "ats", "points": 4, "position": 10, "wins": 0 },
				{ "constructorRef": "osella", "points": 3, "position": 11, "wins": 0 },
				{
					"constructorRef": "fittipaldi",
					"points": 1,
					"position": 12,
					"wins": 0
				},
				{ "constructorRef": "arrows", "points": 0, "position": 13, "wins": 0 },
				{ "constructorRef": "march", "points": 0, "position": 14, "wins": 0 },
				{
					"constructorRef": "theodore",
					"points": 0,
					"position": 15,
					"wins": 0
				},
				{ "constructorRef": "toleman", "points": 0, "position": 16, "wins": 0 },
				{ "constructorRef": "ensign", "points": 0, "position": 17, "wins": 0 }
			],
			"date": "23rd May 1982",
			"driverStandings": [
				{ "driverRef": "prost", "points": 18, "position": 1, "wins": 2 },
				{ "driverRef": "watson", "points": 17, "position": 2, "wins": 1 },
				{ "driverRef": "pironi", "points": 16, "position": 3, "wins": 1 },
				{ "driverRef": "keke_rosberg", "points": 14, "position": 4, "wins": 0 },
				{ "driverRef": "patrese", "points": 13, "position": 5, "wins": 1 },
				{ "driverRef": "lauda", "points": 12, "position": 6, "wins": 1 },
				{ "driverRef": "alboreto", "points": 10, "position": 7, "wins": 0 },
				{ "driverRef": "mansell", "points": 7, "position": 8, "wins": 0 },
				{ "driverRef": "angelis", "points": 7, "position": 9, "wins": 0 },
				{
					"driverRef": "gilles_villeneuve",
					"points": 6,
					"position": 10,
					"wins": 0
				},
				{ "driverRef": "reutemann", "points": 6, "position": 11, "wins": 0 },
				{ "driverRef": "cesaris", "points": 4, "position": 12, "wins": 0 },
				{ "driverRef": "arnoux", "points": 4, "position": 13, "wins": 0 },
				{ "driverRef": "cheever", "points": 4, "position": 14, "wins": 0 },
				{ "driverRef": "jarier", "points": 3, "position": 15, "wins": 0 },
				{ "driverRef": "salazar", "points": 2, "position": 16, "wins": 0 },
				{
					"driverRef": "manfred_winkelhock",
					"points": 2,
					"position": 17,
					"wins": 0
				},
				{ "driverRef": "piquet", "points": 2, "position": 18, "wins": 0 },
				{ "driverRef": "daly", "points": 1, "position": 19, "wins": 0 },
				{ "driverRef": "serra", "points": 1, "position": 20, "wins": 0 },
				{ "driverRef": "surer", "points": 0, "position": 21, "wins": 0 },
				{ "driverRef": "borgudd", "points": 0, "position": 22, "wins": 0 },
				{ "driverRef": "mass", "points": 0, "position": 23, "wins": 0 },
				{ "driverRef": "boesel", "points": 0, "position": 24, "wins": 0 },
				{ "driverRef": "henton", "points": 0, "position": 25, "wins": 0 },
				{ "driverRef": "laffite", "points": 0, "position": 26, "wins": 0 },
				{ "driverRef": "baldi", "points": 0, "position": 27, "wins": 0 },
				{ "driverRef": "giacomelli", "points": 0, "position": 28, "wins": 0 },
				{ "driverRef": "fabi", "points": 0, "position": 29, "wins": 0 },
				{ "driverRef": "paletti", "points": 0, "position": 30, "wins": 0 },
				{ "driverRef": "warwick", "points": 0, "position": 31, "wins": 0 },
				{ "driverRef": "guerrero", "points": 0, "position": 32, "wins": 0 },
				{
					"driverRef": "mario_andretti",
					"points": 0,
					"position": 33,
					"wins": 0
				},
				{ "driverRef": "lammers", "points": 0, "position": 34, "wins": 0 },
				{ "driverRef": "villota", "points": 0, "position": 35, "wins": 0 }
			],
			"name": "Monaco Grand Prix",
			"podium": [
				{ "constructorRef": "brabham", "driverRef": "patrese", "position": 1 },
				{ "constructorRef": "ferrari", "driverRef": "pironi", "position": 2 },
				{ "constructorRef": "alfa", "driverRef": "cesaris", "position": 3 }
			],
			"round": 6,
			"slug": "monaco-grand-prix"
		},
		{
			"circuit": {
				"country": "USA",
				"location": "Detroit",
				"name": "Detroit Street Circuit"
			},
			"constructorStandings": [
				{ "constructorRef": "mclaren", "points": 38, "position": 1, "wins": 3 },
				{ "constructorRef": "ferrari", "points": 26, "position": 2, "wins": 1 },
				{
					"constructorRef": "williams",
					"points": 26,
					"position": 3,
					"wins": 0
				},
				{ "constructorRef": "renault", "points": 22, "position": 4, "wins": 2 },
				{ "constructorRef": "brabham", "points": 15, "position": 5, "wins": 1 },
				{
					"constructorRef": "team_lotus",
					"points": 14,
					"position": 6,
					"wins": 0
				},
				{ "constructorRef": "ligier", "points": 11, "position": 7, "wins": 0 },
				{ "constructorRef": "tyrrell", "points": 10, "position": 8, "wins": 0 },
				{ "constructorRef": "alfa", "points": 4, "position": 9, "wins": 0 },
				{ "constructorRef": "ats", "points": 4, "position": 10, "wins": 0 },
				{ "constructorRef": "osella", "points": 3, "position": 11, "wins": 0 },
				{
					"constructorRef": "fittipaldi",
					"points": 1,
					"position": 12,
					"wins": 0
				},
				{ "constructorRef": "march", "points": 0, "position": 13, "wins": 0 },
				{ "constructorRef": "arrows", "points": 0, "position": 14, "wins": 0 },
				{
					"constructorRef": "theodore",
					"points": 0,
					"position": 15,
					"wins": 0
				},
				{ "constructorRef": "toleman", "points": 0, "position": 16, "wins": 0 },
				{ "constructorRef": "ensign", "points": 0, "position": 17, "wins": 0 }
			],
			"date": "6th Jun 1982",
			"driverStandings": [
				{ "driverRef": "watson", "points": 26, "position": 1, "wins": 2 },
				{ "driverRef": "pironi", "points": 20, "position": 2, "wins": 1 },
				{ "driverRef": "prost", "points": 18, "position": 3, "wins": 2 },
				{ "driverRef": "keke_rosberg", "points": 17, "position": 4, "wins": 0 },
				{ "driverRef": "patrese", "points": 13, "position": 5, "wins": 1 },
				{ "driverRef": "lauda", "points": 12, "position": 6, "wins": 1 },
				{ "driverRef": "cheever", "points": 10, "position": 7, "wins": 0 },
				{ "driverRef": "alboreto", "points": 10, "position": 8, "wins": 0 },
				{ "driverRef": "mansell", "points": 7, "position": 9, "wins": 0 },
				{ "driverRef": "angelis", "points": 7, "position": 10, "wins": 0 },
				{
					"driverRef": "gilles_villeneuve",
					"points": 6,
					"position": 11,
					"wins": 0
				},
				{ "driverRef": "reutemann", "points": 6, "position": 12, "wins": 0 },
				{ "driverRef": "arnoux", "points": 4, "position": 13, "wins": 0 },
				{ "driverRef": "cesaris", "points": 4, "position": 14, "wins": 0 },
				{ "driverRef": "jarier", "points": 3, "position": 15, "wins": 0 },
				{ "driverRef": "daly", "points": 3, "position": 16, "wins": 0 },
				{ "driverRef": "salazar", "points": 2, "position": 17, "wins": 0 },
				{
					"driverRef": "manfred_winkelhock",
					"points": 2,
					"position": 18,
					"wins": 0
				},
				{ "driverRef": "piquet", "points": 2, "position": 19, "wins": 0 },
				{ "driverRef": "laffite", "points": 1, "position": 20, "wins": 0 },
				{ "driverRef": "serra", "points": 1, "position": 21, "wins": 0 },
				{ "driverRef": "mass", "points": 0, "position": 22, "wins": 0 },
				{ "driverRef": "surer", "points": 0, "position": 23, "wins": 0 },
				{ "driverRef": "borgudd", "points": 0, "position": 24, "wins": 0 },
				{ "driverRef": "boesel", "points": 0, "position": 25, "wins": 0 },
				{ "driverRef": "henton", "points": 0, "position": 26, "wins": 0 },
				{ "driverRef": "baldi", "points": 0, "position": 27, "wins": 0 },
				{ "driverRef": "giacomelli", "points": 0, "position": 28, "wins": 0 },
				{ "driverRef": "fabi", "points": 0, "position": 29, "wins": 0 },
				{ "driverRef": "paletti", "points": 0, "position": 30, "wins": 0 },
				{ "driverRef": "warwick", "points": 0, "position": 31, "wins": 0 },
				{ "driverRef": "guerrero", "points": 0, "position": 32, "wins": 0 },
				{
					"driverRef": "mario_andretti",
					"points": 0,
					"position": 33,
					"wins": 0
				},
				{ "driverRef": "lammers", "points": 0, "position": 34, "wins": 0 },
				{ "driverRef": "villota", "points": 0, "position": 35, "wins": 0 }
			],
			"name": "Detroit Grand Prix",
			"podium": [
				{ "constructorRef": "mclaren", "driverRef": "watson", "position": 1 },
				{ "constructorRef": "ligier", "driverRef": "cheever", "position": 2 },
				{ "constructorRef": "ferrari", "driverRef": "pironi", "position": 3 }
			],
			"round": 7,
			"slug": "detroit-grand-prix"
		},
		{
			"circuit": {
				"country": "Canada",
				"location": "Montreal",
				"name": "Circuit Gilles Villeneuve"
			},
			"constructorStandings": [
				{ "constructorRef": "mclaren", "points": 42, "position": 1, "wins": 3 },
				{ "constructorRef": "brabham", "points": 30, "position": 2, "wins": 2 },
				{ "constructorRef": "ferrari", "points": 26, "position": 3, "wins": 1 },
				{
					"constructorRef": "williams",
					"points": 26,
					"position": 4,
					"wins": 0
				},
				{ "constructorRef": "renault", "points": 22, "position": 5, "wins": 2 },
				{
					"constructorRef": "team_lotus",
					"points": 17,
					"position": 6,
					"wins": 0
				},
				{ "constructorRef": "ligier", "points": 11, "position": 7, "wins": 0 },
				{ "constructorRef": "tyrrell", "points": 10, "position": 8, "wins": 0 },
				{ "constructorRef": "alfa", "points": 5, "position": 9, "wins": 0 },
				{ "constructorRef": "ats", "points": 4, "position": 10, "wins": 0 },
				{ "constructorRef": "osella", "points": 3, "position": 11, "wins": 0 },
				{ "constructorRef": "arrows", "points": 2, "position": 12, "wins": 0 },
				{
					"constructorRef": "fittipaldi",
					"points": 1,
					"position": 13,
					"wins": 0
				},
				{ "constructorRef": "march", "points": 0, "position": 14, "wins": 0 },
				{
					"constructorRef": "theodore",
					"points": 0,
					"position": 15,
					"wins": 0
				},
				{ "constructorRef": "toleman", "points": 0, "position": 16, "wins": 0 },
				{ "constructorRef": "ensign", "points": 0, "position": 17, "wins": 0 }
			],
			"date": "13th Jun 1982",
			"driverStandings": [
				{ "driverRef": "watson", "points": 30, "position": 1, "wins": 2 },
				{ "driverRef": "pironi", "points": 20, "position": 2, "wins": 1 },
				{ "driverRef": "patrese", "points": 19, "position": 3, "wins": 1 },
				{ "driverRef": "prost", "points": 18, "position": 4, "wins": 2 },
				{ "driverRef": "keke_rosberg", "points": 17, "position": 5, "wins": 0 },
				{ "driverRef": "lauda", "points": 12, "position": 6, "wins": 1 },
				{ "driverRef": "piquet", "points": 11, "position": 7, "wins": 1 },
				{ "driverRef": "cheever", "points": 10, "position": 8, "wins": 0 },
				{ "driverRef": "alboreto", "points": 10, "position": 9, "wins": 0 },
				{ "driverRef": "angelis", "points": 10, "position": 10, "wins": 0 },
				{ "driverRef": "mansell", "points": 7, "position": 11, "wins": 0 },
				{
					"driverRef": "gilles_villeneuve",
					"points": 6,
					"position": 12,
					"wins": 0
				},
				{ "driverRef": "reutemann", "points": 6, "position": 13, "wins": 0 },
				{ "driverRef": "cesaris", "points": 5, "position": 14, "wins": 0 },
				{ "driverRef": "arnoux", "points": 4, "position": 15, "wins": 0 },
				{ "driverRef": "jarier", "points": 3, "position": 16, "wins": 0 },
				{ "driverRef": "daly", "points": 3, "position": 17, "wins": 0 },
				{ "driverRef": "surer", "points": 2, "position": 18, "wins": 0 },
				{ "driverRef": "salazar", "points": 2, "position": 19, "wins": 0 },
				{
					"driverRef": "manfred_winkelhock",
					"points": 2,
					"position": 20,
					"wins": 0
				},
				{ "driverRef": "laffite", "points": 1, "position": 21, "wins": 0 },
				{ "driverRef": "serra", "points": 1, "position": 22, "wins": 0 },
				{ "driverRef": "mass", "points": 0, "position": 23, "wins": 0 },
				{ "driverRef": "borgudd", "points": 0, "position": 24, "wins": 0 },
				{ "driverRef": "boesel", "points": 0, "position": 25, "wins": 0 },
				{ "driverRef": "henton", "points": 0, "position": 26, "wins": 0 },
				{ "driverRef": "baldi", "points": 0, "position": 27, "wins": 0 },
				{ "driverRef": "giacomelli", "points": 0, "position": 28, "wins": 0 },
				{ "driverRef": "fabi", "points": 0, "position": 29, "wins": 0 },
				{ "driverRef": "paletti", "points": 0, "position": 30, "wins": 0 },
				{ "driverRef": "warwick", "points": 0, "position": 31, "wins": 0 },
				{ "driverRef": "guerrero", "points": 0, "position": 32, "wins": 0 },
				{
					"driverRef": "mario_andretti",
					"points": 0,
					"position": 33,
					"wins": 0
				},
				{ "driverRef": "lammers", "points": 0, "position": 34, "wins": 0 },
				{ "driverRef": "lees", "points": 0, "position": 35, "wins": 0 },
				{ "driverRef": "villota", "points": 0, "position": 36, "wins": 0 }
			],
			"name": "Canadian Grand Prix",
			"podium": [
				{ "constructorRef": "brabham", "driverRef": "piquet", "position": 1 },
				{ "constructorRef": "brabham", "driverRef": "patrese", "position": 2 },
				{ "constructorRef": "mclaren", "driverRef": "watson", "position": 3 }
			],
			"round": 8,
			"slug": "canadian-grand-prix"
		},
		{
			"circuit": {
				"country": "Netherlands",
				"location": "Zandvoort",
				"name": "Circuit Park Zandvoort"
			},
			"constructorStandings": [
				{ "constructorRef": "mclaren", "points": 45, "position": 1, "wins": 3 },
				{ "constructorRef": "brabham", "points": 36, "position": 2, "wins": 2 },
				{ "constructorRef": "ferrari", "points": 35, "position": 3, "wins": 2 },
				{
					"constructorRef": "williams",
					"points": 32,
					"position": 4,
					"wins": 0
				},
				{ "constructorRef": "renault", "points": 22, "position": 5, "wins": 2 },
				{
					"constructorRef": "team_lotus",
					"points": 17,
					"position": 6,
					"wins": 0
				},
				{ "constructorRef": "ligier", "points": 11, "position": 7, "wins": 0 },
				{ "constructorRef": "tyrrell", "points": 10, "position": 8, "wins": 0 },
				{ "constructorRef": "alfa", "points": 5, "position": 9, "wins": 0 },
				{ "constructorRef": "ats", "points": 4, "position": 10, "wins": 0 },
				{ "constructorRef": "osella", "points": 3, "position": 11, "wins": 0 },
				{ "constructorRef": "arrows", "points": 3, "position": 12, "wins": 0 },
				{
					"constructorRef": "fittipaldi",
					"points": 1,
					"position": 13,
					"wins": 0
				},
				{ "constructorRef": "march", "points": 0, "position": 14, "wins": 0 },
				{
					"constructorRef": "theodore",
					"points": 0,
					"position": 15,
					"wins": 0
				},
				{ "constructorRef": "toleman", "points": 0, "position": 16, "wins": 0 },
				{ "constructorRef": "ensign", "points": 0, "position": 17, "wins": 0 }
			],
			"date": "3rd Jul 1982",
			"driverStandings": [
				{ "driverRef": "watson", "points": 30, "position": 1, "wins": 2 },
				{ "driverRef": "pironi", "points": 29, "position": 2, "wins": 2 },
				{ "driverRef": "keke_rosberg", "points": 21, "position": 3, "wins": 0 },
				{ "driverRef": "patrese", "points": 19, "position": 4, "wins": 1 },
				{ "driverRef": "prost", "points": 18, "position": 5, "wins": 2 },
				{ "driverRef": "piquet", "points": 17, "position": 6, "wins": 1 },
				{ "driverRef": "lauda", "points": 15, "position": 7, "wins": 1 },
				{ "driverRef": "cheever", "points": 10, "position": 8, "wins": 0 },
				{ "driverRef": "alboreto", "points": 10, "position": 9, "wins": 0 },
				{ "driverRef": "angelis", "points": 10, "position": 10, "wins": 0 },
				{ "driverRef": "mansell", "points": 7, "position": 11, "wins": 0 },
				{
					"driverRef": "gilles_villeneuve",
					"points": 6,
					"position": 12,
					"wins": 0
				},
				{ "driverRef": "reutemann", "points": 6, "position": 13, "wins": 0 },
				{ "driverRef": "cesaris", "points": 5, "position": 14, "wins": 0 },
				{ "driverRef": "daly", "points": 5, "position": 15, "wins": 0 },
				{ "driverRef": "arnoux", "points": 4, "position": 16, "wins": 0 },
				{ "driverRef": "jarier", "points": 3, "position": 17, "wins": 0 },
				{ "driverRef": "surer", "points": 2, "position": 18, "wins": 0 },
				{ "driverRef": "salazar", "points": 2, "position": 19, "wins": 0 },
				{
					"driverRef": "manfred_winkelhock",
					"points": 2,
					"position": 20,
					"wins": 0
				},
				{ "driverRef": "baldi", "points": 1, "position": 21, "wins": 0 },
				{ "driverRef": "laffite", "points": 1, "position": 22, "wins": 0 },
				{ "driverRef": "serra", "points": 1, "position": 23, "wins": 0 },
				{ "driverRef": "mass", "points": 0, "position": 24, "wins": 0 },
				{ "driverRef": "borgudd", "points": 0, "position": 25, "wins": 0 },
				{ "driverRef": "boesel", "points": 0, "position": 26, "wins": 0 },
				{ "driverRef": "henton", "points": 0, "position": 27, "wins": 0 },
				{ "driverRef": "tambay", "points": 0, "position": 28, "wins": 0 },
				{ "driverRef": "giacomelli", "points": 0, "position": 29, "wins": 0 },
				{ "driverRef": "fabi", "points": 0, "position": 30, "wins": 0 },
				{ "driverRef": "paletti", "points": 0, "position": 31, "wins": 0 },
				{ "driverRef": "warwick", "points": 0, "position": 32, "wins": 0 },
				{ "driverRef": "guerrero", "points": 0, "position": 33, "wins": 0 },
				{ "driverRef": "lammers", "points": 0, "position": 34, "wins": 0 },
				{
					"driverRef": "mario_andretti",
					"points": 0,
					"position": 35,
					"wins": 0
				},
				{ "driverRef": "lees", "points": 0, "position": 36, "wins": 0 },
				{ "driverRef": "villota", "points": 0, "position": 37, "wins": 0 },
				{ "driverRef": "moreno", "points": 0, "position": 38, "wins": 0 }
			],
			"name": "Dutch Grand Prix",
			"podium": [
				{ "constructorRef": "ferrari", "driverRef": "pironi", "position": 1 },
				{ "constructorRef": "brabham", "driverRef": "piquet", "position": 2 },
				{
					"constructorRef": "williams",
					"driverRef": "keke_rosberg",
					"position": 3
				}
			],
			"round": 9,
			"slug": "dutch-grand-prix"
		},
		{
			"circuit": {
				"country": "UK",
				"location": "Kent",
				"name": "Brands Hatch"
			},
			"constructorStandings": [
				{ "constructorRef": "mclaren", "points": 54, "position": 1, "wins": 4 },
				{ "constructorRef": "ferrari", "points": 45, "position": 2, "wins": 2 },
				{ "constructorRef": "brabham", "points": 36, "position": 3, "wins": 2 },
				{
					"constructorRef": "williams",
					"points": 34,
					"position": 4,
					"wins": 0
				},
				{ "constructorRef": "renault", "points": 23, "position": 5, "wins": 2 },
				{
					"constructorRef": "team_lotus",
					"points": 20,
					"position": 6,
					"wins": 0
				},
				{ "constructorRef": "ligier", "points": 11, "position": 7, "wins": 0 },
				{ "constructorRef": "tyrrell", "points": 10, "position": 8, "wins": 0 },
				{ "constructorRef": "alfa", "points": 5, "position": 9, "wins": 0 },
				{ "constructorRef": "ats", "points": 4, "position": 10, "wins": 0 },
				{ "constructorRef": "osella", "points": 3, "position": 11, "wins": 0 },
				{ "constructorRef": "arrows", "points": 3, "position": 12, "wins": 0 },
				{
					"constructorRef": "fittipaldi",
					"points": 1,
					"position": 13,
					"wins": 0
				},
				{ "constructorRef": "march", "points": 0, "position": 14, "wins": 0 },
				{
					"constructorRef": "theodore",
					"points": 0,
					"position": 15,
					"wins": 0
				},
				{ "constructorRef": "toleman", "points": 0, "position": 16, "wins": 0 },
				{ "constructorRef": "ensign", "points": 0, "position": 17, "wins": 0 }
			],
			"date": "18th Jul 1982",
			"driverStandings": [
				{ "driverRef": "pironi", "points": 35, "position": 1, "wins": 2 },
				{ "driverRef": "watson", "points": 30, "position": 2, "wins": 2 },
				{ "driverRef": "lauda", "points": 24, "position": 3, "wins": 2 },
				{ "driverRef": "keke_rosberg", "points": 21, "position": 4, "wins": 0 },
				{ "driverRef": "prost", "points": 19, "position": 5, "wins": 2 },
				{ "driverRef": "patrese", "points": 19, "position": 6, "wins": 1 },
				{ "driverRef": "piquet", "points": 17, "position": 7, "wins": 1 },
				{ "driverRef": "angelis", "points": 13, "position": 8, "wins": 0 },
				{ "driverRef": "cheever", "points": 10, "position": 9, "wins": 0 },
				{ "driverRef": "alboreto", "points": 10, "position": 10, "wins": 0 },
				{ "driverRef": "mansell", "points": 7, "position": 11, "wins": 0 },
				{ "driverRef": "daly", "points": 7, "position": 12, "wins": 0 },
				{
					"driverRef": "gilles_villeneuve",
					"points": 6,
					"position": 13,
					"wins": 0
				},
				{ "driverRef": "reutemann", "points": 6, "position": 14, "wins": 0 },
				{ "driverRef": "cesaris", "points": 5, "position": 15, "wins": 0 },
				{ "driverRef": "tambay", "points": 4, "position": 16, "wins": 0 },
				{ "driverRef": "arnoux", "points": 4, "position": 17, "wins": 0 },
				{ "driverRef": "jarier", "points": 3, "position": 18, "wins": 0 },
				{ "driverRef": "surer", "points": 2, "position": 19, "wins": 0 },
				{ "driverRef": "salazar", "points": 2, "position": 20, "wins": 0 },
				{
					"driverRef": "manfred_winkelhock",
					"points": 2,
					"position": 21,
					"wins": 0
				},
				{ "driverRef": "baldi", "points": 1, "position": 22, "wins": 0 },
				{ "driverRef": "laffite", "points": 1, "position": 23, "wins": 0 },
				{ "driverRef": "serra", "points": 1, "position": 24, "wins": 0 },
				{ "driverRef": "mass", "points": 0, "position": 25, "wins": 0 },
				{ "driverRef": "borgudd", "points": 0, "position": 26, "wins": 0 },
				{ "driverRef": "giacomelli", "points": 0, "position": 27, "wins": 0 },
				{ "driverRef": "henton", "points": 0, "position": 28, "wins": 0 },
				{ "driverRef": "boesel", "points": 0, "position": 29, "wins": 0 },
				{ "driverRef": "fabi", "points": 0, "position": 30, "wins": 0 },
				{ "driverRef": "paletti", "points": 0, "position": 31, "wins": 0 },
				{ "driverRef": "warwick", "points": 0, "position": 32, "wins": 0 },
				{ "driverRef": "guerrero", "points": 0, "position": 33, "wins": 0 },
				{ "driverRef": "lammers", "points": 0, "position": 34, "wins": 0 },
				{
					"driverRef": "mario_andretti",
					"points": 0,
					"position": 35,
					"wins": 0
				},
				{ "driverRef": "lees", "points": 0, "position": 36, "wins": 0 },
				{ "driverRef": "villota", "points": 0, "position": 37, "wins": 0 },
				{ "driverRef": "moreno", "points": 0, "position": 38, "wins": 0 }
			],
			"name": "British Grand Prix",
			"podium": [
				{ "constructorRef": "mclaren", "driverRef": "lauda", "position": 1 },
				{ "constructorRef": "ferrari", "driverRef": "pironi", "position": 2 },
				{ "constructorRef": "ferrari", "driverRef": "tambay", "position": 3 }
			],
			"round": 10,
			"slug": "british-grand-prix"
		},
		{
			"circuit": {
				"country": "France",
				"location": "Le Castellet",
				"name": "Circuit Paul Ricard"
			},
			"constructorStandings": [
				{ "constructorRef": "mclaren", "points": 54, "position": 1, "wins": 4 },
				{ "constructorRef": "ferrari", "points": 52, "position": 2, "wins": 2 },
				{ "constructorRef": "renault", "points": 38, "position": 3, "wins": 3 },
				{ "constructorRef": "brabham", "points": 36, "position": 4, "wins": 2 },
				{
					"constructorRef": "williams",
					"points": 36,
					"position": 5,
					"wins": 0
				},
				{
					"constructorRef": "team_lotus",
					"points": 20,
					"position": 6,
					"wins": 0
				},
				{ "constructorRef": "ligier", "points": 11, "position": 7, "wins": 0 },
				{ "constructorRef": "tyrrell", "points": 11, "position": 8, "wins": 0 },
				{ "constructorRef": "alfa", "points": 5, "position": 9, "wins": 0 },
				{ "constructorRef": "ats", "points": 4, "position": 10, "wins": 0 },
				{ "constructorRef": "osella", "points": 3, "position": 11, "wins": 0 },
				{ "constructorRef": "arrows", "points": 3, "position": 12, "wins": 0 },
				{
					"constructorRef": "fittipaldi",
					"points": 1,
					"position": 13,
					"wins": 0
				},
				{ "constructorRef": "march", "points": 0, "position": 14, "wins": 0 },
				{
					"constructorRef": "theodore",
					"points": 0,
					"position": 15,
					"wins": 0
				},
				{ "constructorRef": "toleman", "points": 0, "position": 16, "wins": 0 },
				{ "constructorRef": "ensign", "points": 0, "position": 17, "wins": 0 }
			],
			"date": "25th Jul 1982",
			"driverStandings": [
				{ "driverRef": "pironi", "points": 39, "position": 1, "wins": 2 },
				{ "driverRef": "watson", "points": 30, "position": 2, "wins": 2 },
				{ "driverRef": "prost", "points": 25, "position": 3, "wins": 2 },
				{ "driverRef": "lauda", "points": 24, "position": 4, "wins": 2 },
				{ "driverRef": "keke_rosberg", "points": 23, "position": 5, "wins": 0 },
				{ "driverRef": "patrese", "points": 19, "position": 6, "wins": 1 },
				{ "driverRef": "piquet", "points": 17, "position": 7, "wins": 1 },
				{ "driverRef": "arnoux", "points": 13, "position": 8, "wins": 1 },
				{ "driverRef": "angelis", "points": 13, "position": 9, "wins": 0 },
				{ "driverRef": "alboreto", "points": 11, "position": 10, "wins": 0 },
				{ "driverRef": "cheever", "points": 10, "position": 11, "wins": 0 },
				{ "driverRef": "mansell", "points": 7, "position": 12, "wins": 0 },
				{ "driverRef": "tambay", "points": 7, "position": 13, "wins": 0 },
				{ "driverRef": "daly", "points": 7, "position": 14, "wins": 0 },
				{
					"driverRef": "gilles_villeneuve",
					"points": 6,
					"position": 15,
					"wins": 0
				},
				{ "driverRef": "reutemann", "points": 6, "position": 16, "wins": 0 },
				{ "driverRef": "cesaris", "points": 5, "position": 17, "wins": 0 },
				{ "driverRef": "jarier", "points": 3, "position": 18, "wins": 0 },
				{ "driverRef": "surer", "points": 2, "position": 19, "wins": 0 },
				{ "driverRef": "salazar", "points": 2, "position": 20, "wins": 0 },
				{
					"driverRef": "manfred_winkelhock",
					"points": 2,
					"position": 21,
					"wins": 0
				},
				{ "driverRef": "baldi", "points": 1, "position": 22, "wins": 0 },
				{ "driverRef": "laffite", "points": 1, "position": 23, "wins": 0 },
				{ "driverRef": "serra", "points": 1, "position": 24, "wins": 0 },
				{ "driverRef": "mass", "points": 0, "position": 25, "wins": 0 },
				{ "driverRef": "giacomelli", "points": 0, "position": 26, "wins": 0 },
				{ "driverRef": "borgudd", "points": 0, "position": 27, "wins": 0 },
				{ "driverRef": "henton", "points": 0, "position": 28, "wins": 0 },
				{ "driverRef": "boesel", "points": 0, "position": 29, "wins": 0 },
				{ "driverRef": "lees", "points": 0, "position": 30, "wins": 0 },
				{ "driverRef": "warwick", "points": 0, "position": 31, "wins": 0 },
				{ "driverRef": "fabi", "points": 0, "position": 32, "wins": 0 },
				{ "driverRef": "paletti", "points": 0, "position": 33, "wins": 0 },
				{ "driverRef": "guerrero", "points": 0, "position": 34, "wins": 0 },
				{ "driverRef": "lammers", "points": 0, "position": 35, "wins": 0 },
				{
					"driverRef": "mario_andretti",
					"points": 0,
					"position": 36,
					"wins": 0
				},
				{ "driverRef": "villota", "points": 0, "position": 37, "wins": 0 },
				{ "driverRef": "moreno", "points": 0, "position": 38, "wins": 0 }
			],
			"name": "French Grand Prix",
			"podium": [
				{ "constructorRef": "renault", "driverRef": "arnoux", "position": 1 },
				{ "constructorRef": "renault", "driverRef": "prost", "position": 2 },
				{ "constructorRef": "ferrari", "driverRef": "pironi", "position": 3 }
			],
			"round": 11,
			"slug": "french-grand-prix"
		},
		{
			"circuit": {
				"country": "Germany",
				"location": "Hockenheim",
				"name": "Hockenheimring"
			},
			"constructorStandings": [
				{ "constructorRef": "ferrari", "points": 61, "position": 1, "wins": 3 },
				{ "constructorRef": "mclaren", "points": 54, "position": 2, "wins": 4 },
				{ "constructorRef": "renault", "points": 44, "position": 3, "wins": 3 },
				{
					"constructorRef": "williams",
					"points": 40,
					"position": 4,
					"wins": 0
				},
				{ "constructorRef": "brabham", "points": 36, "position": 5, "wins": 2 },
				{
					"constructorRef": "team_lotus",
					"points": 20,
					"position": 6,
					"wins": 0
				},
				{ "constructorRef": "tyrrell", "points": 14, "position": 7, "wins": 0 },
				{ "constructorRef": "ligier", "points": 11, "position": 8, "wins": 0 },
				{ "constructorRef": "alfa", "points": 7, "position": 9, "wins": 0 },
				{ "constructorRef": "ats", "points": 4, "position": 10, "wins": 0 },
				{ "constructorRef": "arrows", "points": 4, "position": 11, "wins": 0 },
				{ "constructorRef": "osella", "points": 3, "position": 12, "wins": 0 },
				{
					"constructorRef": "fittipaldi",
					"points": 1,
					"position": 13,
					"wins": 0
				},
				{ "constructorRef": "march", "points": 0, "position": 14, "wins": 0 },
				{ "constructorRef": "ensign", "points": 0, "position": 15, "wins": 0 },
				{ "constructorRef": "toleman", "points": 0, "position": 16, "wins": 0 },
				{ "constructorRef": "theodore", "points": 0, "position": 17, "wins": 0 }
			],
			"date": "8th Aug 1982",
			"driverStandings": [
				{ "driverRef": "pironi", "points": 39, "position": 1, "wins": 2 },
				{ "driverRef": "watson", "points": 30, "position": 2, "wins": 2 },
				{ "driverRef": "keke_rosberg", "points": 27, "position": 3, "wins": 0 },
				{ "driverRef": "prost", "points": 25, "position": 4, "wins": 2 },
				{ "driverRef": "lauda", "points": 24, "position": 5, "wins": 2 },
				{ "driverRef": "arnoux", "points": 19, "position": 6, "wins": 1 },
				{ "driverRef": "patrese", "points": 19, "position": 7, "wins": 1 },
				{ "driverRef": "piquet", "points": 17, "position": 8, "wins": 1 },
				{ "driverRef": "tambay", "points": 16, "position": 9, "wins": 1 },
				{ "driverRef": "alboreto", "points": 14, "position": 10, "wins": 0 },
				{ "driverRef": "angelis", "points": 13, "position": 11, "wins": 0 },
				{ "driverRef": "cheever", "points": 10, "position": 12, "wins": 0 },
				{ "driverRef": "mansell", "points": 7, "position": 13, "wins": 0 },
				{ "driverRef": "daly", "points": 7, "position": 14, "wins": 0 },
				{
					"driverRef": "gilles_villeneuve",
					"points": 6,
					"position": 15,
					"wins": 0
				},
				{ "driverRef": "reutemann", "points": 6, "position": 16, "wins": 0 },
				{ "driverRef": "cesaris", "points": 5, "position": 17, "wins": 0 },
				{ "driverRef": "jarier", "points": 3, "position": 18, "wins": 0 },
				{ "driverRef": "surer", "points": 3, "position": 19, "wins": 0 },
				{ "driverRef": "giacomelli", "points": 2, "position": 20, "wins": 0 },
				{ "driverRef": "salazar", "points": 2, "position": 21, "wins": 0 },
				{
					"driverRef": "manfred_winkelhock",
					"points": 2,
					"position": 22,
					"wins": 0
				},
				{ "driverRef": "baldi", "points": 1, "position": 23, "wins": 0 },
				{ "driverRef": "laffite", "points": 1, "position": 24, "wins": 0 },
				{ "driverRef": "serra", "points": 1, "position": 25, "wins": 0 },
				{ "driverRef": "henton", "points": 0, "position": 26, "wins": 0 },
				{ "driverRef": "mass", "points": 0, "position": 27, "wins": 0 },
				{ "driverRef": "borgudd", "points": 0, "position": 28, "wins": 0 },
				{ "driverRef": "boesel", "points": 0, "position": 29, "wins": 0 },
				{ "driverRef": "guerrero", "points": 0, "position": 30, "wins": 0 },
				{ "driverRef": "warwick", "points": 0, "position": 31, "wins": 0 },
				{ "driverRef": "lees", "points": 0, "position": 32, "wins": 0 },
				{ "driverRef": "fabi", "points": 0, "position": 33, "wins": 0 },
				{ "driverRef": "paletti", "points": 0, "position": 34, "wins": 0 },
				{ "driverRef": "lammers", "points": 0, "position": 35, "wins": 0 },
				{
					"driverRef": "mario_andretti",
					"points": 0,
					"position": 36,
					"wins": 0
				},
				{ "driverRef": "villota", "points": 0, "position": 37, "wins": 0 },
				{ "driverRef": "byrne", "points": 0, "position": 38, "wins": 0 },
				{ "driverRef": "keegan", "points": 0, "position": 39, "wins": 0 },
				{ "driverRef": "moreno", "points": 0, "position": 40, "wins": 0 }
			],
			"name": "German Grand Prix",
			"podium": [
				{ "constructorRef": "ferrari", "driverRef": "tambay", "position": 1 },
				{ "constructorRef": "renault", "driverRef": "arnoux", "position": 2 },
				{
					"constructorRef": "williams",
					"driverRef": "keke_rosberg",
					"position": 3
				}
			],
			"round": 12,
			"slug": "german-grand-prix"
		},
		{
			"circuit": {
				"country": "Austria",
				"location": "Spielberg",
				"name": "Red Bull Ring"
			},
			"constructorStandings": [
				{ "constructorRef": "ferrari", "points": 64, "position": 1, "wins": 3 },
				{ "constructorRef": "mclaren", "points": 56, "position": 2, "wins": 4 },
				{
					"constructorRef": "williams",
					"points": 46,
					"position": 3,
					"wins": 0
				},
				{ "constructorRef": "renault", "points": 44, "position": 4, "wins": 3 },
				{ "constructorRef": "brabham", "points": 36, "position": 5, "wins": 2 },
				{
					"constructorRef": "team_lotus",
					"points": 29,
					"position": 6,
					"wins": 1
				},
				{ "constructorRef": "ligier", "points": 15, "position": 7, "wins": 0 },
				{ "constructorRef": "tyrrell", "points": 14, "position": 8, "wins": 0 },
				{ "constructorRef": "alfa", "points": 7, "position": 9, "wins": 0 },
				{ "constructorRef": "arrows", "points": 5, "position": 10, "wins": 0 },
				{ "constructorRef": "ats", "points": 4, "position": 11, "wins": 0 },
				{ "constructorRef": "osella", "points": 3, "position": 12, "wins": 0 },
				{
					"constructorRef": "fittipaldi",
					"points": 1,
					"position": 13,
					"wins": 0
				},
				{ "constructorRef": "march", "points": 0, "position": 14, "wins": 0 },
				{ "constructorRef": "ensign", "points": 0, "position": 15, "wins": 0 },
				{ "constructorRef": "toleman", "points": 0, "position": 16, "wins": 0 },
				{ "constructorRef": "theodore", "points": 0, "position": 17, "wins": 0 }
			],
			"date": "15th Aug 1982",
			"driverStandings": [
				{ "driverRef": "pironi", "points": 39, "position": 1, "wins": 2 },
				{ "driverRef": "keke_rosberg", "points": 33, "position": 2, "wins": 0 },
				{ "driverRef": "watson", "points": 30, "position": 3, "wins": 2 },
				{ "driverRef": "lauda", "points": 26, "position": 4, "wins": 2 },
				{ "driverRef": "prost", "points": 25, "position": 5, "wins": 2 },
				{ "driverRef": "angelis", "points": 22, "position": 6, "wins": 1 },
				{ "driverRef": "arnoux", "points": 19, "position": 7, "wins": 1 },
				{ "driverRef": "patrese", "points": 19, "position": 8, "wins": 1 },
				{ "driverRef": "tambay", "points": 19, "position": 9, "wins": 1 },
				{ "driverRef": "piquet", "points": 17, "position": 10, "wins": 1 },
				{ "driverRef": "alboreto", "points": 14, "position": 11, "wins": 0 },
				{ "driverRef": "cheever", "points": 10, "position": 12, "wins": 0 },
				{ "driverRef": "mansell", "points": 7, "position": 13, "wins": 0 },
				{ "driverRef": "daly", "points": 7, "position": 14, "wins": 0 },
				{
					"driverRef": "gilles_villeneuve",
					"points": 6,
					"position": 15,
					"wins": 0
				},
				{ "driverRef": "reutemann", "points": 6, "position": 16, "wins": 0 },
				{ "driverRef": "laffite", "points": 5, "position": 17, "wins": 0 },
				{ "driverRef": "cesaris", "points": 5, "position": 18, "wins": 0 },
				{ "driverRef": "jarier", "points": 3, "position": 19, "wins": 0 },
				{ "driverRef": "surer", "points": 3, "position": 20, "wins": 0 },
				{ "driverRef": "giacomelli", "points": 2, "position": 21, "wins": 0 },
				{ "driverRef": "salazar", "points": 2, "position": 22, "wins": 0 },
				{
					"driverRef": "manfred_winkelhock",
					"points": 2,
					"position": 23,
					"wins": 0
				},
				{ "driverRef": "baldi", "points": 2, "position": 24, "wins": 0 },
				{ "driverRef": "serra", "points": 1, "position": 25, "wins": 0 },
				{ "driverRef": "henton", "points": 0, "position": 26, "wins": 0 },
				{ "driverRef": "mass", "points": 0, "position": 27, "wins": 0 },
				{ "driverRef": "borgudd", "points": 0, "position": 28, "wins": 0 },
				{ "driverRef": "boesel", "points": 0, "position": 29, "wins": 0 },
				{ "driverRef": "guerrero", "points": 0, "position": 30, "wins": 0 },
				{ "driverRef": "warwick", "points": 0, "position": 31, "wins": 0 },
				{ "driverRef": "lees", "points": 0, "position": 32, "wins": 0 },
				{ "driverRef": "fabi", "points": 0, "position": 33, "wins": 0 },
				{ "driverRef": "paletti", "points": 0, "position": 34, "wins": 0 },
				{ "driverRef": "byrne", "points": 0, "position": 35, "wins": 0 },
				{ "driverRef": "lammers", "points": 0, "position": 36, "wins": 0 },
				{
					"driverRef": "mario_andretti",
					"points": 0,
					"position": 37,
					"wins": 0
				},
				{ "driverRef": "keegan", "points": 0, "position": 38, "wins": 0 },
				{ "driverRef": "villota", "points": 0, "position": 39, "wins": 0 },
				{ "driverRef": "moreno", "points": 0, "position": 40, "wins": 0 }
			],
			"name": "Austrian Grand Prix",
			"podium": [
				{
					"constructorRef": "team_lotus",
					"driverRef": "angelis",
					"position": 1
				},
				{
					"constructorRef": "williams",
					"driverRef": "keke_rosberg",
					"position": 2
				},
				{ "constructorRef": "ligier", "driverRef": "laffite", "position": 3 }
			],
			"round": 13,
			"slug": "austrian-grand-prix"
		},
		{
			"circuit": {
				"country": "France",
				"location": "Dijon",
				"name": "Dijon-Prenois"
			},
			"constructorStandings": [
				{ "constructorRef": "ferrari", "points": 64, "position": 1, "wins": 3 },
				{ "constructorRef": "mclaren", "points": 60, "position": 2, "wins": 4 },
				{
					"constructorRef": "williams",
					"points": 55,
					"position": 3,
					"wins": 1
				},
				{ "constructorRef": "renault", "points": 50, "position": 4, "wins": 3 },
				{ "constructorRef": "brabham", "points": 41, "position": 5, "wins": 2 },
				{
					"constructorRef": "team_lotus",
					"points": 30,
					"position": 6,
					"wins": 1
				},
				{ "constructorRef": "ligier", "points": 15, "position": 7, "wins": 0 },
				{ "constructorRef": "tyrrell", "points": 14, "position": 8, "wins": 0 },
				{ "constructorRef": "alfa", "points": 7, "position": 9, "wins": 0 },
				{ "constructorRef": "arrows", "points": 5, "position": 10, "wins": 0 },
				{ "constructorRef": "ats", "points": 4, "position": 11, "wins": 0 },
				{ "constructorRef": "osella", "points": 3, "position": 12, "wins": 0 },
				{
					"constructorRef": "fittipaldi",
					"points": 1,
					"position": 13,
					"wins": 0
				},
				{ "constructorRef": "march", "points": 0, "position": 14, "wins": 0 },
				{ "constructorRef": "ensign", "points": 0, "position": 15, "wins": 0 },
				{ "constructorRef": "toleman", "points": 0, "position": 16, "wins": 0 },
				{ "constructorRef": "theodore", "points": 0, "position": 17, "wins": 0 }
			],
			"date": "29th Aug 1982",
			"driverStandings": [
				{ "driverRef": "keke_rosberg", "points": 42, "position": 1, "wins": 1 },
				{ "driverRef": "pironi", "points": 39, "position": 2, "wins": 2 },
				{ "driverRef": "prost", "points": 31, "position": 3, "wins": 2 },
				{ "driverRef": "watson", "points": 30, "position": 4, "wins": 2 },
				{ "driverRef": "lauda", "points": 30, "position": 5, "wins": 2 },
				{ "driverRef": "angelis", "points": 23, "position": 6, "wins": 1 },
				{ "driverRef": "patrese", "points": 21, "position": 7, "wins": 1 },
				{ "driverRef": "piquet", "points": 20, "position": 8, "wins": 1 },
				{ "driverRef": "arnoux", "points": 19, "position": 9, "wins": 1 },
				{ "driverRef": "tambay", "points": 19, "position": 10, "wins": 1 },
				{ "driverRef": "alboreto", "points": 14, "position": 11, "wins": 0 },
				{ "driverRef": "cheever", "points": 10, "position": 12, "wins": 0 },
				{ "driverRef": "mansell", "points": 7, "position": 13, "wins": 0 },
				{ "driverRef": "daly", "points": 7, "position": 14, "wins": 0 },
				{
					"driverRef": "gilles_villeneuve",
					"points": 6,
					"position": 15,
					"wins": 0
				},
				{ "driverRef": "reutemann", "points": 6, "position": 16, "wins": 0 },
				{ "driverRef": "laffite", "points": 5, "position": 17, "wins": 0 },
				{ "driverRef": "cesaris", "points": 5, "position": 18, "wins": 0 },
				{ "driverRef": "jarier", "points": 3, "position": 19, "wins": 0 },
				{ "driverRef": "surer", "points": 3, "position": 20, "wins": 0 },
				{ "driverRef": "giacomelli", "points": 2, "position": 21, "wins": 0 },
				{ "driverRef": "salazar", "points": 2, "position": 22, "wins": 0 },
				{
					"driverRef": "manfred_winkelhock",
					"points": 2,
					"position": 23,
					"wins": 0
				},
				{ "driverRef": "baldi", "points": 2, "position": 24, "wins": 0 },
				{ "driverRef": "serra", "points": 1, "position": 25, "wins": 0 },
				{ "driverRef": "henton", "points": 0, "position": 26, "wins": 0 },
				{ "driverRef": "mass", "points": 0, "position": 27, "wins": 0 },
				{ "driverRef": "borgudd", "points": 0, "position": 28, "wins": 0 },
				{ "driverRef": "boesel", "points": 0, "position": 29, "wins": 0 },
				{ "driverRef": "guerrero", "points": 0, "position": 30, "wins": 0 },
				{ "driverRef": "warwick", "points": 0, "position": 31, "wins": 0 },
				{ "driverRef": "lees", "points": 0, "position": 32, "wins": 0 },
				{ "driverRef": "fabi", "points": 0, "position": 33, "wins": 0 },
				{ "driverRef": "paletti", "points": 0, "position": 34, "wins": 0 },
				{ "driverRef": "byrne", "points": 0, "position": 35, "wins": 0 },
				{ "driverRef": "lammers", "points": 0, "position": 36, "wins": 0 },
				{
					"driverRef": "mario_andretti",
					"points": 0,
					"position": 37,
					"wins": 0
				},
				{ "driverRef": "keegan", "points": 0, "position": 38, "wins": 0 },
				{ "driverRef": "villota", "points": 0, "position": 39, "wins": 0 },
				{ "driverRef": "moreno", "points": 0, "position": 40, "wins": 0 }
			],
			"name": "Swiss Grand Prix",
			"podium": [
				{
					"constructorRef": "williams",
					"driverRef": "keke_rosberg",
					"position": 1
				},
				{ "constructorRef": "renault", "driverRef": "prost", "position": 2 },
				{ "constructorRef": "mclaren", "driverRef": "lauda", "position": 3 }
			],
			"round": 14,
			"slug": "swiss-grand-prix"
		},
		{
			"circuit": {
				"country": "Italy",
				"location": "Monza",
				"name": "Autodromo Nazionale di Monza"
			},
			"constructorStandings": [
				{ "constructorRef": "ferrari", "points": 74, "position": 1, "wins": 3 },
				{ "constructorRef": "mclaren", "points": 63, "position": 2, "wins": 4 },
				{ "constructorRef": "renault", "points": 59, "position": 3, "wins": 4 },
				{
					"constructorRef": "williams",
					"points": 55,
					"position": 4,
					"wins": 1
				},
				{ "constructorRef": "brabham", "points": 41, "position": 5, "wins": 2 },
				{
					"constructorRef": "team_lotus",
					"points": 30,
					"position": 6,
					"wins": 1
				},
				{ "constructorRef": "ligier", "points": 16, "position": 7, "wins": 0 },
				{ "constructorRef": "tyrrell", "points": 16, "position": 8, "wins": 0 },
				{ "constructorRef": "alfa", "points": 7, "position": 9, "wins": 0 },
				{ "constructorRef": "arrows", "points": 5, "position": 10, "wins": 0 },
				{ "constructorRef": "ats", "points": 4, "position": 11, "wins": 0 },
				{ "constructorRef": "osella", "points": 3, "position": 12, "wins": 0 },
				{
					"constructorRef": "fittipaldi",
					"points": 1,
					"position": 13,
					"wins": 0
				},
				{ "constructorRef": "march", "points": 0, "position": 14, "wins": 0 },
				{ "constructorRef": "ensign", "points": 0, "position": 15, "wins": 0 },
				{ "constructorRef": "toleman", "points": 0, "position": 16, "wins": 0 },
				{ "constructorRef": "theodore", "points": 0, "position": 17, "wins": 0 }
			],
			"date": "12th Sep 1982",
			"driverStandings": [
				{ "driverRef": "keke_rosberg", "points": 42, "position": 1, "wins": 1 },
				{ "driverRef": "pironi", "points": 39, "position": 2, "wins": 2 },
				{ "driverRef": "watson", "points": 33, "position": 3, "wins": 2 },
				{ "driverRef": "prost", "points": 31, "position": 4, "wins": 2 },
				{ "driverRef": "lauda", "points": 30, "position": 5, "wins": 2 },
				{ "driverRef": "arnoux", "points": 28, "position": 6, "wins": 2 },
				{ "driverRef": "tambay", "points": 25, "position": 7, "wins": 1 },
				{ "driverRef": "angelis", "points": 23, "position": 8, "wins": 1 },
				{ "driverRef": "patrese", "points": 21, "position": 9, "wins": 1 },
				{ "driverRef": "piquet", "points": 20, "position": 10, "wins": 1 },
				{ "driverRef": "alboreto", "points": 16, "position": 11, "wins": 0 },
				{ "driverRef": "cheever", "points": 11, "position": 12, "wins": 0 },
				{ "driverRef": "mansell", "points": 7, "position": 13, "wins": 0 },
				{ "driverRef": "daly", "points": 7, "position": 14, "wins": 0 },
				{
					"driverRef": "gilles_villeneuve",
					"points": 6,
					"position": 15,
					"wins": 0
				},
				{ "driverRef": "reutemann", "points": 6, "position": 16, "wins": 0 },
				{ "driverRef": "laffite", "points": 5, "position": 17, "wins": 0 },
				{ "driverRef": "cesaris", "points": 5, "position": 18, "wins": 0 },
				{
					"driverRef": "mario_andretti",
					"points": 4,
					"position": 19,
					"wins": 0
				},
				{ "driverRef": "jarier", "points": 3, "position": 20, "wins": 0 },
				{ "driverRef": "surer", "points": 3, "position": 21, "wins": 0 },
				{ "driverRef": "giacomelli", "points": 2, "position": 22, "wins": 0 },
				{ "driverRef": "salazar", "points": 2, "position": 23, "wins": 0 },
				{
					"driverRef": "manfred_winkelhock",
					"points": 2,
					"position": 24,
					"wins": 0
				},
				{ "driverRef": "baldi", "points": 2, "position": 25, "wins": 0 },
				{ "driverRef": "serra", "points": 1, "position": 26, "wins": 0 },
				{ "driverRef": "henton", "points": 0, "position": 27, "wins": 0 },
				{ "driverRef": "mass", "points": 0, "position": 28, "wins": 0 },
				{ "driverRef": "borgudd", "points": 0, "position": 29, "wins": 0 },
				{ "driverRef": "boesel", "points": 0, "position": 30, "wins": 0 },
				{ "driverRef": "guerrero", "points": 0, "position": 31, "wins": 0 },
				{ "driverRef": "warwick", "points": 0, "position": 32, "wins": 0 },
				{ "driverRef": "lees", "points": 0, "position": 33, "wins": 0 },
				{ "driverRef": "fabi", "points": 0, "position": 34, "wins": 0 },
				{ "driverRef": "paletti", "points": 0, "position": 35, "wins": 0 },
				{ "driverRef": "byrne", "points": 0, "position": 36, "wins": 0 },
				{ "driverRef": "lammers", "points": 0, "position": 37, "wins": 0 },
				{ "driverRef": "keegan", "points": 0, "position": 38, "wins": 0 },
				{ "driverRef": "villota", "points": 0, "position": 39, "wins": 0 },
				{ "driverRef": "moreno", "points": 0, "position": 40, "wins": 0 }
			],
			"name": "Italian Grand Prix",
			"podium": [
				{ "constructorRef": "renault", "driverRef": "arnoux", "position": 1 },
				{ "constructorRef": "ferrari", "driverRef": "tambay", "position": 2 },
				{
					"constructorRef": "ferrari",
					"driverRef": "mario_andretti",
					"position": 3
				}
			],
			"round": 15,
			"slug": "italian-grand-prix"
		},
		{
			"circuit": {
				"country": "USA",
				"location": "Nevada",
				"name": "Las Vegas Street Circuit"
			},
			"constructorStandings": [
				{ "constructorRef": "ferrari", "points": 74, "position": 1, "wins": 3 },
				{ "constructorRef": "mclaren", "points": 69, "position": 2, "wins": 4 },
				{ "constructorRef": "renault", "points": 62, "position": 3, "wins": 4 },
				{
					"constructorRef": "williams",
					"points": 58,
					"position": 4,
					"wins": 1
				},
				{ "constructorRef": "brabham", "points": 41, "position": 5, "wins": 2 },
				{
					"constructorRef": "team_lotus",
					"points": 30,
					"position": 6,
					"wins": 1
				},
				{ "constructorRef": "tyrrell", "points": 25, "position": 7, "wins": 1 },
				{ "constructorRef": "ligier", "points": 20, "position": 8, "wins": 0 },
				{ "constructorRef": "alfa", "points": 7, "position": 9, "wins": 0 },
				{ "constructorRef": "arrows", "points": 5, "position": 10, "wins": 0 },
				{ "constructorRef": "ats", "points": 4, "position": 11, "wins": 0 },
				{ "constructorRef": "osella", "points": 3, "position": 12, "wins": 0 },
				{
					"constructorRef": "fittipaldi",
					"points": 1,
					"position": 13,
					"wins": 0
				},
				{ "constructorRef": "march", "points": 0, "position": 14, "wins": 0 },
				{ "constructorRef": "ensign", "points": 0, "position": 15, "wins": 0 },
				{ "constructorRef": "toleman", "points": 0, "position": 16, "wins": 0 },
				{ "constructorRef": "theodore", "points": 0, "position": 17, "wins": 0 }
			],
			"date": "25th Sep 1982",
			"driverStandings": [
				{ "driverRef": "keke_rosberg", "points": 44, "position": 1, "wins": 1 },
				{ "driverRef": "pironi", "points": 39, "position": 2, "wins": 2 },
				{ "driverRef": "watson", "points": 39, "position": 3, "wins": 2 },
				{ "driverRef": "prost", "points": 34, "position": 4, "wins": 2 },
				{ "driverRef": "lauda", "points": 30, "position": 5, "wins": 2 },
				{ "driverRef": "arnoux", "points": 28, "position": 6, "wins": 2 },
				{ "driverRef": "tambay", "points": 25, "position": 7, "wins": 1 },
				{ "driverRef": "alboreto", "points": 25, "position": 8, "wins": 1 },
				{ "driverRef": "angelis", "points": 23, "position": 9, "wins": 1 },
				{ "driverRef": "patrese", "points": 21, "position": 10, "wins": 1 },
				{ "driverRef": "piquet", "points": 20, "position": 11, "wins": 1 },
				{ "driverRef": "cheever", "points": 15, "position": 12, "wins": 0 },
				{ "driverRef": "daly", "points": 8, "position": 13, "wins": 0 },
				{ "driverRef": "mansell", "points": 7, "position": 14, "wins": 0 },
				{
					"driverRef": "gilles_villeneuve",
					"points": 6,
					"position": 15,
					"wins": 0
				},
				{ "driverRef": "reutemann", "points": 6, "position": 16, "wins": 0 },
				{ "driverRef": "cesaris", "points": 5, "position": 17, "wins": 0 },
				{ "driverRef": "laffite", "points": 5, "position": 18, "wins": 0 },
				{
					"driverRef": "mario_andretti",
					"points": 4,
					"position": 19,
					"wins": 0
				},
				{ "driverRef": "jarier", "points": 3, "position": 20, "wins": 0 },
				{ "driverRef": "surer", "points": 3, "position": 21, "wins": 0 },
				{ "driverRef": "giacomelli", "points": 2, "position": 22, "wins": 0 },
				{ "driverRef": "salazar", "points": 2, "position": 23, "wins": 0 },
				{
					"driverRef": "manfred_winkelhock",
					"points": 2,
					"position": 24,
					"wins": 0
				},
				{ "driverRef": "baldi", "points": 2, "position": 25, "wins": 0 },
				{ "driverRef": "serra", "points": 1, "position": 26, "wins": 0 },
				{ "driverRef": "henton", "points": 0, "position": 27, "wins": 0 },
				{ "driverRef": "mass", "points": 0, "position": 28, "wins": 0 },
				{ "driverRef": "borgudd", "points": 0, "position": 29, "wins": 0 },
				{ "driverRef": "boesel", "points": 0, "position": 30, "wins": 0 },
				{ "driverRef": "guerrero", "points": 0, "position": 31, "wins": 0 },
				{ "driverRef": "warwick", "points": 0, "position": 32, "wins": 0 },
				{ "driverRef": "keegan", "points": 0, "position": 33, "wins": 0 },
				{ "driverRef": "lees", "points": 0, "position": 34, "wins": 0 },
				{ "driverRef": "fabi", "points": 0, "position": 35, "wins": 0 },
				{ "driverRef": "paletti", "points": 0, "position": 36, "wins": 0 },
				{ "driverRef": "byrne", "points": 0, "position": 37, "wins": 0 },
				{ "driverRef": "lammers", "points": 0, "position": 38, "wins": 0 },
				{ "driverRef": "villota", "points": 0, "position": 39, "wins": 0 },
				{ "driverRef": "moreno", "points": 0, "position": 40, "wins": 0 }
			],
			"name": "Caesars Palace Grand Prix",
			"podium": [
				{ "constructorRef": "tyrrell", "driverRef": "alboreto", "position": 1 },
				{ "constructorRef": "mclaren", "driverRef": "watson", "position": 2 },
				{ "constructorRef": "ligier", "driverRef": "cheever", "position": 3 }
			],
			"round": 16,
			"slug": "caesars-palace-grand-prix"
		}
	],
	"teams": [
		{
			"constructorRef": "alfa",
			"drivers": [
				{
					"driverRef": "giacomelli",
					"name": "Bruno Giacomelli",
					"nationality": "Italian"
				},
				{
					"driverRef": "cesaris",
					"name": "Andrea de Cesaris",
					"nationality": "Italian"
				}
			],
			"name": "Alfa Romeo",
			"nationality": "Swiss"
		},
		{
			"constructorRef": "arrows",
			"drivers": [
				{
					"driverRef": "baldi",
					"name": "Mauro Baldi",
					"nationality": "Italian"
				},
				{
					"driverRef": "henton",
					"name": "Brian Henton",
					"nationality": "British"
				},
				{ "driverRef": "surer", "name": "Marc Surer", "nationality": "Swiss" }
			],
			"name": "Arrows",
			"nationality": "British"
		},
		{
			"constructorRef": "ats",
			"drivers": [
				{
					"driverRef": "salazar",
					"name": "Eliseo Salazar",
					"nationality": "Chilean"
				},
				{
					"driverRef": "manfred_winkelhock",
					"name": "Manfred Winkelhock",
					"nationality": "German"
				}
			],
			"name": "ATS",
			"nationality": "Italian"
		},
		{
			"constructorRef": "brabham",
			"drivers": [
				{
					"driverRef": "patrese",
					"name": "Riccardo Patrese",
					"nationality": "Italian"
				},
				{
					"driverRef": "piquet",
					"name": "Nelson Piquet",
					"nationality": "Brazilian"
				}
			],
			"name": "Brabham",
			"nationality": "British"
		},
		{
			"constructorRef": "ensign",
			"drivers": [
				{
					"driverRef": "guerrero",
					"name": "Roberto Guerrero",
					"nationality": "Colombian"
				}
			],
			"name": "Ensign",
			"nationality": "British"
		},
		{
			"constructorRef": "ferrari",
			"drivers": [
				{
					"driverRef": "pironi",
					"name": "Didier Pironi",
					"nationality": "French"
				},
				{
					"driverRef": "gilles_villeneuve",
					"name": "Gilles Villeneuve",
					"nationality": "Canadian"
				},
				{
					"driverRef": "tambay",
					"name": "Patrick Tambay",
					"nationality": "French"
				},
				{
					"driverRef": "mario_andretti",
					"name": "Mario Andretti",
					"nationality": "American"
				}
			],
			"name": "Ferrari",
			"nationality": "Italian"
		},
		{
			"constructorRef": "fittipaldi",
			"drivers": [
				{
					"driverRef": "serra",
					"name": "Chico Serra",
					"nationality": "Brazilian"
				}
			],
			"name": "Fittipaldi",
			"nationality": "Brazilian"
		},
		{
			"constructorRef": "ligier",
			"drivers": [
				{
					"driverRef": "laffite",
					"name": "Jacques Laffite",
					"nationality": "French"
				},
				{
					"driverRef": "cheever",
					"name": "Eddie Cheever",
					"nationality": "American"
				}
			],
			"name": "Ligier",
			"nationality": "French"
		},
		{
			"constructorRef": "march",
			"drivers": [
				{ "driverRef": "mass", "name": "Jochen Mass", "nationality": "German" },
				{
					"driverRef": "boesel",
					"name": "Raul Boesel",
					"nationality": "Brazilian"
				},
				{
					"driverRef": "villota",
					"name": "Emilio de Villota",
					"nationality": "Spanish"
				},
				{
					"driverRef": "keegan",
					"name": "Rupert Keegan",
					"nationality": "British"
				}
			],
			"name": "March",
			"nationality": "British"
		},
		{
			"constructorRef": "mclaren",
			"drivers": [
				{
					"driverRef": "lauda",
					"name": "Niki Lauda",
					"nationality": "Austrian"
				},
				{
					"driverRef": "watson",
					"name": "John Watson",
					"nationality": "British"
				}
			],
			"name": "McLaren",
			"nationality": "British"
		},
		{
			"constructorRef": "osella",
			"drivers": [
				{
					"driverRef": "jarier",
					"name": "Jean-Pierre Jarier",
					"nationality": "French"
				},
				{
					"driverRef": "paletti",
					"name": "Riccardo Paletti",
					"nationality": "Italian"
				}
			],
			"name": "Osella",
			"nationality": "Italian"
		},
		{
			"constructorRef": "renault",
			"drivers": [
				{
					"driverRef": "prost",
					"name": "Alain Prost",
					"nationality": "French"
				},
				{
					"driverRef": "arnoux",
					"name": "René Arnoux",
					"nationality": "French"
				}
			],
			"name": "Renault",
			"nationality": "French"
		},
		{
			"constructorRef": "team_lotus",
			"drivers": [
				{
					"driverRef": "angelis",
					"name": "Elio de Angelis",
					"nationality": "Italian"
				},
				{
					"driverRef": "mansell",
					"name": "Nigel Mansell",
					"nationality": "British"
				},
				{
					"driverRef": "moreno",
					"name": "Roberto Moreno",
					"nationality": "Brazilian"
				},
				{ "driverRef": "lees", "name": "Geoff Lees", "nationality": "British" }
			],
			"name": "Team Lotus",
			"nationality": "British"
		},
		{
			"constructorRef": "theodore",
			"drivers": [
				{ "driverRef": "daly", "name": "Derek Daly", "nationality": "Irish" },
				{
					"driverRef": "lammers",
					"name": "Jan Lammers",
					"nationality": "Dutch"
				},
				{ "driverRef": "lees", "name": "Geoff Lees", "nationality": "British" },
				{ "driverRef": "byrne", "name": "Tommy Byrne", "nationality": "Irish" }
			],
			"name": "Theodore",
			"nationality": "Hong Kong"
		},
		{
			"constructorRef": "toleman",
			"drivers": [
				{
					"driverRef": "warwick",
					"name": "Derek Warwick",
					"nationality": "British"
				},
				{ "driverRef": "fabi", "name": "Teo Fabi", "nationality": "Italian" }
			],
			"name": "Toleman",
			"nationality": "British"
		},
		{
			"constructorRef": "tyrrell",
			"drivers": [
				{
					"driverRef": "alboreto",
					"name": "Michele Alboreto",
					"nationality": "Italian"
				},
				{
					"driverRef": "borgudd",
					"name": "Slim Borgudd",
					"nationality": "Swedish"
				},
				{
					"driverRef": "henton",
					"name": "Brian Henton",
					"nationality": "British"
				}
			],
			"name": "Tyrrell",
			"nationality": "British"
		},
		{
			"constructorRef": "williams",
			"drivers": [
				{
					"driverRef": "reutemann",
					"name": "Carlos Reutemann",
					"nationality": "Argentine"
				},
				{
					"driverRef": "keke_rosberg",
					"name": "Keke Rosberg",
					"nationality": "Finnish"
				},
				{
					"driverRef": "mario_andretti",
					"name": "Mario Andretti",
					"nationality": "American"
				},
				{ "driverRef": "daly", "name": "Derek Daly", "nationality": "Irish" }
			],
			"name": "Williams",
			"nationality": "British"
		}
	],
	"year": 1982
}
