{
	"championshipStandings": [
		{ "position": 43, "year": 1970 },
		{ "position": 28, "year": 1971 },
		{ "position": 33, "year": 1972 },
		{ "position": 27, "year": 1973 }
	],
	"code": null,
	"dob": "1940-10-02",
	"driverId": 330,
	"driverRef": "galli",
	"image": "https://upload.wikimedia.org/wikipedia/commons/thumb/1/17/Nanni_Galli%2C_Alfa_Romeo_33.3%2C_1971-05-29.jpg/220px-Nanni_Galli%2C_Alfa_Romeo_33.3%2C_1971-05-29.jpg",
	"lapsLead": 0,
	"name": "Nanni Galli",
	"nationality": "Italian",
	"podiums": 0,
	"poles": 0,
	"raceWins": 0,
	"seasons": [
		{
			"results": [{ "constructor": "McLaren-Alfa Romeo", "points": 0, "position": null, "round": 10, "roundName": "Italian Grand Prix" }],
			"year": 1970
		},
		{
			"results": [
				{ "constructor": "March-Ford", "points": 0, "position": 11, "round": 6, "roundName": "British Grand Prix" },
				{ "constructor": "March-Alfa Romeo", "points": 0, "position": 12, "round": 7, "roundName": "German Grand Prix" },
				{ "constructor": "March-Alfa Romeo", "points": 0, "position": 12, "round": 8, "roundName": "Austrian Grand Prix" },
				{ "constructor": "March-Ford", "points": 0, "position": null, "round": 9, "roundName": "Italian Grand Prix" },
				{ "constructor": "March-Ford", "points": 0, "position": 16, "round": 10, "roundName": "Canadian Grand Prix" },
				{ "constructor": "March-Ford", "points": 0, "position": null, "round": 11, "roundName": "United States Grand Prix" }
			],
			"year": 1971
		},
		{
			"results": [
				{ "constructor": "Tecno", "points": 0, "position": null, "round": 5, "roundName": "Belgian Grand Prix" },
				{ "constructor": "Ferrari", "points": 0, "position": 13, "round": 6, "roundName": "French Grand Prix" },
				{ "constructor": "Tecno", "points": 0, "position": null, "round": 7, "roundName": "British Grand Prix" },
				{ "constructor": "Tecno", "points": 0, "position": null, "round": 9, "roundName": "Austrian Grand Prix" },
				{ "constructor": "Tecno", "points": 0, "position": null, "round": 10, "roundName": "Italian Grand Prix" }
			],
			"year": 1972
		},
		{
			"results": [
				{ "constructor": "Iso Marlboro", "points": 0, "position": null, "round": 1, "roundName": "Argentine Grand Prix" },
				{ "constructor": "Iso Marlboro", "points": 0, "position": 9, "round": 2, "roundName": "Brazilian Grand Prix" },
				{ "constructor": "Iso Marlboro", "points": 0, "position": 11, "round": 4, "roundName": "Spanish Grand Prix" },
				{ "constructor": "Iso Marlboro", "points": 0, "position": null, "round": 5, "roundName": "Belgian Grand Prix" },
				{ "constructor": "Iso Marlboro", "points": 0, "position": null, "round": 6, "roundName": "Monaco Grand Prix" }
			],
			"year": 1973
		}
	],
	"totalLaps": 0,
	"totalRaces": 17
}
