{
	"championshipStanding": 25,
	"results": [
		{
			"constructor": "Team Lotus",
			"points": 0,
			"position": null,
			"round": 2,
			"roundName": "Monaco Grand Prix"
		},
		{
			"constructor": "Team Lotus",
			"points": 0,
			"position": null,
			"round": 3,
			"roundName": "Dutch Grand Prix"
		},
		{
			"constructor": "Team Lotus",
			"points": 0,
			"position": null,
			"round": 5,
			"roundName": "Belgian Grand Prix"
		},
		{
			"constructor": "Team Lotus",
			"points": 0,
			"position": null,
			"round": 6,
			"roundName": "French Grand Prix"
		},
		{
			"constructor": "Team Lotus",
			"points": 0,
			"position": null,
			"round": 7,
			"roundName": "British Grand Prix"
		},
		{
			"constructor": "Team Lotus",
			"points": 0,
			"position": null,
			"round": 8,
			"roundName": "German Grand Prix"
		},
		{
			"constructor": "Team Lotus",
			"points": 0,
			"position": null,
			"round": 9,
			"roundName": "Portuguese Grand Prix"
		},
		{
			"constructor": "Team Lotus",
			"points": 0,
			"position": 6,
			"round": 10,
			"roundName": "Italian Grand Prix"
		},
		{
			"constructor": "Team Lotus",
			"points": 0,
			"position": 16,
			"round": 11,
			"roundName": "Moroccan Grand Prix"
		}
	]
}
