{
  "raceId": 952,
  "year": 2016,
  "round": 5,
  "name": "Spanish Grand Prix",
  "date": "2016-05-15",
  "time": "12:00:00",
  "circuit": {
    "name": "Circuit de Barcelona-Catalunya",
    "location": "Montmeló",
    "country": "Spain"
  },
  "winnerDriver": "max_verstappen",
  "winnerConstructor": "red_bull",
  "driverStandings": [
    {
      "driverRef": "rosberg",
      "position": 1,
      "points": 100,
      "wins": 4
    },
    {
      "driverRef": "raikkonen",
      "position": 2,
      "points": 61,
      "wins": 0
    },
    {
      "driverRef": "hamilton",
      "position": 3,
      "points": 57,
      "wins": 0
    },
    {
      "driverRef": "vettel",
      "position": 4,
      "points": 48,
      "wins": 0
    },
    {
      "driverRef": "ricciardo",
      "position": 5,
      "points": 48,
      "wins": 0
    },
    {
      "driverRef": "max_verstappen",
      "position": 6,
      "points": 38,
      "wins": 1
    },
    {
      "driverRef": "massa",
      "position": 7,
      "points": 36,
      "wins": 0
    },
    {
      "driverRef": "bottas",
      "position": 8,
      "points": 29,
      "wins": 0
    },
    {
      "driverRef": "kvyat",
      "position": 9,
      "points": 22,
      "wins": 0
    },
    {
      "driverRef": "grosjean",
      "position": 10,
      "points": 22,
      "wins": 0
    },
    {
      "driverRef": "sainz",
      "position": 11,
      "points": 12,
      "wins": 0
    },
    {
      "driverRef": "alonso",
      "position": 12,
      "points": 8,
      "wins": 0
    },
    {
      "driverRef": "perez",
      "position": 13,
      "points": 8,
      "wins": 0
    },
    {
      "driverRef": "kevin_magnussen",
      "position": 14,
      "points": 6,
      "wins": 0
    },
    {
      "driverRef": "hulkenberg",
      "position": 15,
      "points": 6,
      "wins": 0
    },
    {
      "driverRef": "button",
      "position": 16,
      "points": 3,
      "wins": 0
    },
    {
      "driverRef": "vandoorne",
      "position": 17,
      "points": 1,
      "wins": 0
    },
    {
      "driverRef": "jolyon_palmer",
      "position": 18,
      "points": 0,
      "wins": 0
    },
    {
      "driverRef": "gutierrez",
      "position": 19,
      "points": 0,
      "wins": 0
    },
    {
      "driverRef": "ericsson",
      "position": 20,
      "points": 0,
      "wins": 0
    },
    {
      "driverRef": "wehrlein",
      "position": 21,
      "points": 0,
      "wins": 0
    },
    {
      "driverRef": "nasr",
      "position": 22,
      "points": 0,
      "wins": 0
    },
    {
      "driverRef": "haryanto",
      "position": 23,
      "points": 0,
      "wins": 0
    }
  ],
  "constructorStandings": [
    {
      "constructorRef": "mercedes",
      "position": 1,
      "points": 157,
      "wins": 4
    },
    {
      "constructorRef": "ferrari",
      "position": 2,
      "points": 109,
      "wins": 0
    },
    {
      "constructorRef": "red_bull",
      "position": 3,
      "points": 94,
      "wins": 1
    },
    {
      "constructorRef": "williams",
      "position": 4,
      "points": 65,
      "wins": 0
    },
    {
      "constructorRef": "toro_rosso",
      "position": 5,
      "points": 26,
      "wins": 0
    },
    {
      "constructorRef": "haas",
      "position": 6,
      "points": 22,
      "wins": 0
    },
    {
      "constructorRef": "force_india",
      "position": 7,
      "points": 14,
      "wins": 0
    },
    {
      "constructorRef": "mclaren",
      "position": 8,
      "points": 12,
      "wins": 0
    },
    {
      "constructorRef": "renault",
      "position": 9,
      "points": 6,
      "wins": 0
    },
    {
      "constructorRef": "sauber",
      "position": 10,
      "points": 0,
      "wins": 0
    },
    {
      "constructorRef": "manor",
      "position": 11,
      "points": 0,
      "wins": 0
    }
  ]
}