{
	"circuit": {
		"circuitRef": "galvez",
		"country": "Argentina",
		"location": "Buenos Aires",
		"name": "Autódromo Juan y Oscar Gálvez"
	},
	"date": "1997-04-13",
	"driversData": [
		{
			"constructorRef": "williams",
			"driverRef": "villeneuve",
			"grid": 1,
			"points": 10,
			"position": 1,
			"positionOrder": 1,
			"positionText": "1",
			"qualifying": { "position": 1, "q1": "1:24.473", "q2": null, "q3": null }
		},
		{
			"constructorRef": "ferrari",
			"driverRef": "irvine",
			"grid": 7,
			"points": 6,
			"position": 2,
			"positionOrder": 2,
			"positionText": "2",
			"qualifying": { "position": 7, "q1": "1:26.327", "q2": null, "q3": null }
		},
		{
			"constructorRef": "jordan",
			"driverRef": "ralf_schumacher",
			"grid": 6,
			"points": 4,
			"position": 3,
			"positionOrder": 3,
			"positionText": "3",
			"qualifying": { "position": 6, "q1": "1:26.218", "q2": null, "q3": null }
		},
		{
			"constructorRef": "sauber",
			"driverRef": "herbert",
			"grid": 8,
			"points": 3,
			"position": 4,
			"positionOrder": 4,
			"positionText": "4",
			"qualifying": { "position": 8, "q1": "1:26.564", "q2": null, "q3": null }
		},
		{
			"constructorRef": "mclaren",
			"driverRef": "hakkinen",
			"grid": 17,
			"points": 2,
			"position": 5,
			"positionOrder": 5,
			"positionText": "5",
			"qualifying": { "position": 17, "q1": "1:28.135", "q2": null, "q3": null }
		},
		{
			"constructorRef": "benetton",
			"driverRef": "berger",
			"grid": 12,
			"points": 1,
			"position": 6,
			"positionOrder": 6,
			"positionText": "6",
			"qualifying": { "position": 12, "q1": "1:27.259", "q2": null, "q3": null }
		},
		{
			"constructorRef": "benetton",
			"driverRef": "alesi",
			"grid": 11,
			"points": 0,
			"position": 7,
			"positionOrder": 7,
			"positionText": "7",
			"qualifying": { "position": 11, "q1": "1:27.076", "q2": null, "q3": null }
		},
		{
			"constructorRef": "tyrrell",
			"driverRef": "salo",
			"grid": 19,
			"points": 0,
			"position": 8,
			"positionOrder": 8,
			"positionText": "8",
			"qualifying": { "position": 19, "q1": "1:28.224", "q2": null, "q3": null }
		},
		{
			"constructorRef": "minardi",
			"driverRef": "trulli",
			"grid": 18,
			"points": 0,
			"position": 9,
			"positionOrder": 9,
			"positionText": "9",
			"qualifying": { "position": 18, "q1": "1:28.160", "q2": null, "q3": null }
		},
		{
			"constructorRef": "stewart",
			"driverRef": "magnussen",
			"grid": 15,
			"points": 0,
			"position": 10,
			"positionOrder": 10,
			"positionText": "10",
			"qualifying": { "position": 15, "q1": "1:28.035", "q2": null, "q3": null }
		},
		{
			"constructorRef": "sauber",
			"driverRef": "larini",
			"grid": 14,
			"points": 0,
			"position": null,
			"positionOrder": 11,
			"positionText": "R",
			"qualifying": { "position": 14, "q1": "1:27.690", "q2": null, "q3": null }
		},
		{
			"constructorRef": "arrows",
			"driverRef": "diniz",
			"grid": 22,
			"points": 0,
			"position": null,
			"positionOrder": 12,
			"positionText": "R",
			"qualifying": { "position": 22, "q1": "1:28.696", "q2": null, "q3": null }
		},
		{
			"constructorRef": "prost",
			"driverRef": "nakano",
			"grid": 20,
			"points": 0,
			"position": null,
			"positionOrder": 13,
			"positionText": "R",
			"qualifying": { "position": 20, "q1": "1:28.366", "q2": null, "q3": null }
		},
		{
			"constructorRef": "tyrrell",
			"driverRef": "verstappen",
			"grid": 16,
			"points": 0,
			"position": null,
			"positionOrder": 14,
			"positionText": "R",
			"qualifying": { "position": 16, "q1": "1:28.094", "q2": null, "q3": null }
		},
		{
			"constructorRef": "minardi",
			"driverRef": "katayama",
			"grid": 21,
			"points": 0,
			"position": null,
			"positionOrder": 15,
			"positionText": "R",
			"qualifying": { "position": 21, "q1": "1:28.413", "q2": null, "q3": null }
		},
		{
			"constructorRef": "arrows",
			"driverRef": "damon_hill",
			"grid": 13,
			"points": 0,
			"position": null,
			"positionOrder": 16,
			"positionText": "R",
			"qualifying": { "position": 13, "q1": "1:27.281", "q2": null, "q3": null }
		},
		{
			"constructorRef": "jordan",
			"driverRef": "fisichella",
			"grid": 9,
			"points": 0,
			"position": null,
			"positionOrder": 17,
			"positionText": "R",
			"qualifying": { "position": 9, "q1": "1:26.619", "q2": null, "q3": null }
		},
		{
			"constructorRef": "stewart",
			"driverRef": "barrichello",
			"grid": 5,
			"points": 0,
			"position": null,
			"positionOrder": 18,
			"positionText": "R",
			"qualifying": { "position": 5, "q1": "1:25.942", "q2": null, "q3": null }
		},
		{
			"constructorRef": "prost",
			"driverRef": "panis",
			"grid": 3,
			"points": 0,
			"position": null,
			"positionOrder": 19,
			"positionText": "R",
			"qualifying": { "position": 3, "q1": "1:25.491", "q2": null, "q3": null }
		},
		{
			"constructorRef": "williams",
			"driverRef": "frentzen",
			"grid": 2,
			"points": 0,
			"position": null,
			"positionOrder": 20,
			"positionText": "R",
			"qualifying": { "position": 2, "q1": "1:25.271", "q2": null, "q3": null }
		},
		{
			"constructorRef": "ferrari",
			"driverRef": "michael_schumacher",
			"grid": 4,
			"points": 0,
			"position": null,
			"positionOrder": 21,
			"positionText": "R",
			"qualifying": { "position": 4, "q1": "1:25.773", "q2": null, "q3": null }
		},
		{
			"constructorRef": "mclaren",
			"driverRef": "coulthard",
			"grid": 10,
			"points": 0,
			"position": null,
			"positionOrder": 22,
			"positionText": "R",
			"qualifying": { "position": 10, "q1": "1:26.799", "q2": null, "q3": null }
		}
	],
	"name": "Argentine Grand Prix",
	"raceId": 209,
	"round": 3,
	"slug": "argentine-grand-prix",
	"year": 1997
}
