{
	"circuit": {
		"circuitRef": "jeddah",
		"country": "Saudi Arabia",
		"location": "Jeddah",
		"name": "Jeddah Corniche Circuit"
	},
	"date": "2023-03-19",
	"driversData": [
		{
			"constructorRef": "red_bull",
			"driverRef": "perez",
			"grid": 1,
			"lapPositions": [],
			"pitStops": [],
			"points": 25,
			"position": 1,
			"positionOrder": 1,
			"positionText": "1"
		},
		{
			"constructorRef": "red_bull",
			"driverRef": "max_verstappen",
			"grid": 15,
			"lapPositions": [],
			"pitStops": [],
			"points": 19,
			"position": 2,
			"positionOrder": 2,
			"positionText": "2"
		},
		{
			"constructorRef": "aston_martin",
			"driverRef": "alonso",
			"grid": 2,
			"lapPositions": [],
			"pitStops": [],
			"points": 15,
			"position": 3,
			"positionOrder": 3,
			"positionText": "3"
		},
		{
			"constructorRef": "mercedes",
			"driverRef": "russell",
			"grid": 3,
			"lapPositions": [],
			"pitStops": [],
			"points": 12,
			"position": 4,
			"positionOrder": 4,
			"positionText": "4"
		},
		{
			"constructorRef": "mercedes",
			"driverRef": "hamilton",
			"grid": 7,
			"lapPositions": [],
			"pitStops": [],
			"points": 10,
			"position": 5,
			"positionOrder": 5,
			"positionText": "5"
		},
		{
			"constructorRef": "ferrari",
			"driverRef": "sainz",
			"grid": 4,
			"lapPositions": [],
			"pitStops": [],
			"points": 8,
			"position": 6,
			"positionOrder": 6,
			"positionText": "6"
		},
		{
			"constructorRef": "ferrari",
			"driverRef": "leclerc",
			"grid": 12,
			"lapPositions": [],
			"pitStops": [],
			"points": 6,
			"position": 7,
			"positionOrder": 7,
			"positionText": "7"
		},
		{
			"constructorRef": "alpine",
			"driverRef": "ocon",
			"grid": 6,
			"lapPositions": [],
			"pitStops": [],
			"points": 4,
			"position": 8,
			"positionOrder": 8,
			"positionText": "8"
		},
		{
			"constructorRef": "alpine",
			"driverRef": "gasly",
			"grid": 9,
			"lapPositions": [],
			"pitStops": [],
			"points": 2,
			"position": 9,
			"positionOrder": 9,
			"positionText": "9"
		},
		{
			"constructorRef": "haas",
			"driverRef": "kevin_magnussen",
			"grid": 13,
			"lapPositions": [],
			"pitStops": [],
			"points": 1,
			"position": 10,
			"positionOrder": 10,
			"positionText": "10"
		},
		{
			"constructorRef": "alphatauri",
			"driverRef": "tsunoda",
			"grid": 16,
			"lapPositions": [],
			"pitStops": [],
			"points": 0,
			"position": 11,
			"positionOrder": 11,
			"positionText": "11"
		},
		{
			"constructorRef": "haas",
			"driverRef": "hulkenberg",
			"grid": 10,
			"lapPositions": [],
			"pitStops": [],
			"points": 0,
			"position": 12,
			"positionOrder": 12,
			"positionText": "12"
		},
		{
			"constructorRef": "alfa",
			"driverRef": "zhou",
			"grid": 11,
			"lapPositions": [],
			"pitStops": [],
			"points": 0,
			"position": 13,
			"positionOrder": 13,
			"positionText": "13"
		},
		{
			"constructorRef": "alphatauri",
			"driverRef": "de_vries",
			"grid": 18,
			"lapPositions": [],
			"pitStops": [],
			"points": 0,
			"position": 14,
			"positionOrder": 14,
			"positionText": "14"
		},
		{
			"constructorRef": "mclaren",
			"driverRef": "piastri",
			"grid": 8,
			"lapPositions": [],
			"pitStops": [],
			"points": 0,
			"position": 15,
			"positionOrder": 15,
			"positionText": "15"
		},
		{
			"constructorRef": "williams",
			"driverRef": "sargeant",
			"grid": 20,
			"lapPositions": [],
			"pitStops": [],
			"points": 0,
			"position": 16,
			"positionOrder": 16,
			"positionText": "16"
		},
		{
			"constructorRef": "mclaren",
			"driverRef": "norris",
			"grid": 19,
			"lapPositions": [],
			"pitStops": [],
			"points": 0,
			"position": 17,
			"positionOrder": 17,
			"positionText": "17"
		},
		{
			"constructorRef": "alfa",
			"driverRef": "bottas",
			"grid": 14,
			"lapPositions": [],
			"pitStops": [],
			"points": 0,
			"position": 18,
			"positionOrder": 18,
			"positionText": "18"
		},
		{
			"constructorRef": "williams",
			"driverRef": "albon",
			"grid": 17,
			"lapPositions": [],
			"pitStops": [],
			"points": 0,
			"position": null,
			"positionOrder": 19,
			"positionText": "R"
		},
		{
			"constructorRef": "aston_martin",
			"driverRef": "stroll",
			"grid": 5,
			"lapPositions": [],
			"pitStops": [],
			"points": 0,
			"position": null,
			"positionOrder": 20,
			"positionText": "R"
		}
	],
	"name": "Saudi Arabian Grand Prix",
	"raceId": 1099,
	"round": 2,
	"year": 2023
}
